{
  "config": "{\"version\":\"5.68\",\"themeCollection\":{\"baseTheme\":{\"name\":\"CY25SU11\",\"type\":2,\"version\":{\"visual\":\"2.4.0\",\"report\":\"3.0.0\",\"page\":\"2.3.0\"}}},\"activeSectionIndex\":0,\"defaultDrillFilterOtherVisuals\":true,\"linguisticSchemaSyncVersion\":2,\"settings\":{\"useNewFilterPaneExperience\":true,\"allowChangeFilterTypes\":true,\"useStylableVisualContainerHeader\":true,\"queryLimitOption\":6,\"useEnhancedTooltips\":true,\"exportDataMode\":1,\"useDefaultAggregateDisplayName\":true,\"filterPaneHiddenInEditMode\":false},\"objects\":{\"section\":[{\"properties\":{\"verticalAlignment\":{\"expr\":{\"Literal\":{\"Value\":\"'Top'\"}}}}}],\"outspacePane\":[{\"properties\":{\"expanded\":{\"expr\":{\"Literal\":{\"Value\":\"false\"}}}}}]}}",
  "layoutOptimization": 0,
  "resourcePackages": [
    {
      "resourcePackage": {
        "disabled": false,
        "items": [
          {
            "name": "CY25SU11",
            "path": "BaseThemes/CY25SU11.json",
            "type": 202
          }
        ],
        "name": "SharedResources",
        "type": 2
      }
    },
    {
      "resourcePackage": {
        "items": [
          {
            "name": "powerbi_layout2550964565433763.png",
            "path": "powerbi_layout2550964565433763.png",
            "type": 100
          }
        ],
        "name": "RegisteredResources",
        "type": 1
      }
    }
  ],
  "sections": [
    {
      "config": "{\"objects\":{\"background\":[{\"properties\":{\"image\":{\"image\":{\"name\":{\"expr\":{\"Literal\":{\"Value\":\"'powerbi_layout.png'\"}}},\"url\":{\"expr\":{\"ResourcePackageItem\":{\"PackageName\":\"RegisteredResources\",\"PackageType\":1,\"ItemName\":\"powerbi_layout2550964565433763.png\"}}},\"scaling\":{\"expr\":{\"Literal\":{\"Value\":\"'Fill'\"}}}}},\"transparency\":{\"expr\":{\"Literal\":{\"Value\":\"0D\"}}}}}]}}",
      "displayName": "Dashboard",
      "displayOption": 1,
      "filters": "[]",
      "height": 758.00,
      "name": "9bae7bd8ec33242f2828",
      "visualContainers": [
        {
          "config": "{\"name\":\"00a0513c3631fe698995\",\"layouts\":[{\"id\":0,\"position\":{\"x\":265.974025974026,\"y\":23.01698301698302,\"z\":0,\"width\":992.2877122877123,\"height\":120.19980019980021,\"tabOrder\":0}}],\"singleVisual\":{\"visualType\":\"cardVisual\",\"projections\":{\"Data\":[{\"queryRef\":\"Measure Table.Total Games\"},{\"queryRef\":\"Measure Table.Free Games\"},{\"queryRef\":\"Measure Table.Total Developers\"},{\"queryRef\":\"Measure Table.AVG Price\"},{\"queryRef\":\"Measure Table.AVG Recommendations\"}]},\"prototypeQuery\":{\"Version\":2,\"From\":[{\"Name\":\"m\",\"Entity\":\"Measure Table\",\"Type\":0}],\"Select\":[{\"Measure\":{\"Expression\":{\"SourceRef\":{\"Source\":\"m\"}},\"Property\":\"Total Games\"},\"Name\":\"Measure Table.Total Games\",\"NativeReferenceName\":\"Total Games\"},{\"Measure\":{\"Expression\":{\"SourceRef\":{\"Source\":\"m\"}},\"Property\":\"AVG Price\"},\"Name\":\"Measure Table.AVG Price\",\"NativeReferenceName\":\"AVG Price\"},{\"Measure\":{\"Expression\":{\"SourceRef\":{\"Source\":\"m\"}},\"Property\":\"AVG Recommendations\"},\"Name\":\"Measure Table.AVG Recommendations\",\"NativeReferenceName\":\"AVG Recommendations\"},{\"Measure\":{\"Expression\":{\"SourceRef\":{\"Source\":\"m\"}},\"Property\":\"Free Games\"},\"Name\":\"Measure Table.Free Games\",\"NativeReferenceName\":\"Free Games\"},{\"Measure\":{\"Expression\":{\"SourceRef\":{\"Source\":\"m\"}},\"Property\":\"Total Developers\"},\"Name\":\"Measure Table.Total Developers\",\"NativeReferenceName\":\"Total Developers\"}],\"OrderBy\":[{\"Direction\":2,\"Expression\":{\"Measure\":{\"Expression\":{\"SourceRef\":{\"Source\":\"m\"}},\"Property\":\"Total Games\"}}}]},\"columnProperties\":{\"Measure Table.Total Games\":{\"formatString\":\"#,0\"},\"Measure Table.Free Games\":{\"formatString\":\"#,0\"},\"Measure Table.Total Developers\":{\"formatString\":\"#,0\"},\"Measure Table.AVG Price\":{\"formatString\":\"\\\\$#,0.00;(\\\\$#,0.00);\\\\$#,0.00\"}},\"drillFilterOtherVisuals\":true,\"hasDefaultSort\":true,\"objects\":{\"layout\":[{\"properties\":{\"columnCount\":{\"expr\":{\"Literal\":{\"Value\":\"5L\"}}}}},{\"properties\":{\"backgroundShow\":{\"expr\":{\"Literal\":{\"Value\":\"false\"}}}},\"selector\":{\"id\":\"default\"}}],\"fillCustom\":[{\"properties\":{\"show\":{\"expr\":{\"Literal\":{\"Value\":\"false\"}}}}}],\"outline\":[{\"properties\":{\"show\":{\"expr\":{\"Literal\":{\"Value\":\"false\"}}}},\"selector\":{\"id\":\"default\"}}],\"accentBar\":[{\"properties\":{\"show\":{\"expr\":{\"Literal\":{\"Value\":\"true\"}}},\"color\":{\"solid\":{\"color\":{\"expr\":{\"Literal\":{\"Value\":\"'#5F9EA0'\"}}}}},\"width\":{\"expr\":{\"Literal\":{\"Value\":\"7D\"}}}},\"selector\":{\"id\":\"default\"}}],\"shadowCustom\":[{\"properties\":{\"show\":{\"expr\":{\"Literal\":{\"Value\":\"false\"}}}},\"selector\":{\"id\":\"default\"}}],\"glowCustom\":[{\"properties\":{\"show\":{\"expr\":{\"Literal\":{\"Value\":\"false\"}}}},\"selector\":{\"id\":\"default\"}}],\"value\":[{\"properties\":{\"fontFamily\":{\"expr\":{\"Literal\":{\"Value\":\"'''Segoe UI Bold'', wf_segoe-ui_bold, helvetica, arial, sans-serif'\"}}},\"fontColor\":{\"solid\":{\"color\":{\"expr\":{\"ThemeDataColor\":{\"ColorId\":1,\"Percent\":0.2}}}}},\"horizontalAlignment\":{\"expr\":{\"Literal\":{\"Value\":\"'center'\"}}},\"showBlankAs\":{\"expr\":{\"Literal\":{\"Value\":\"'0'\"}}}},\"selector\":{\"id\":\"default\"}},{\"properties\":{\"labelDisplayUnits\":{\"expr\":{\"Literal\":{\"Value\":\"1D\"}}},\"labelPrecision\":{\"expr\":{\"Literal\":{\"Value\":\"0L\"}}}},\"selector\":{\"metadata\":\"Measure Table.AVG Recommendations\"}},{\"properties\":{\"labelDisplayUnits\":{\"expr\":{\"Literal\":{\"Value\":\"1D\"}}},\"labelPrecision\":{\"expr\":{\"Literal\":{\"Value\":\"0L\"}}}},\"selector\":{\"metadata\":\"Measure Table.Total Developers\"}},{\"properties\":{\"labelDisplayUnits\":{\"expr\":{\"Literal\":{\"Value\":\"1D\"}}}},\"selector\":{\"metadata\":\"Measure Table.Free Games\"}},{\"properties\":{\"labelDisplayUnits\":{\"expr\":{\"Literal\":{\"Value\":\"1D\"}}}},\"selector\":{\"metadata\":\"Measure Table.Total Games\"}}],\"label\":[{\"properties\":{\"fontColor\":{\"solid\":{\"color\":{\"expr\":{\"ThemeDataColor\":{\"ColorId\":1,\"Percent\":0.2}}}}},\"matchValueAlignment\":{\"expr\":{\"Literal\":{\"Value\":\"false\"}}},\"position\":{\"expr\":{\"Literal\":{\"Value\":\"'aboveValue'\"}}}},\"selector\":{\"id\":\"default\"}},{\"properties\":{\"text\":{\"expr\":{\"Literal\":{\"Value\":\"'Recommendations'\"}}}},\"selector\":{\"metadata\":\"Measure Table.AVG Recommendations\"}},{\"properties\":{\"text\":{\"expr\":{\"Literal\":{\"Value\":\"'Average Price'\"}}}},\"selector\":{\"metadata\":\"Measure Table.AVG Price\"}}],\"spacing\":[{\"properties\":{\"verticalSpacing\":{\"expr\":{\"Literal\":{\"Value\":\"7L\"}}}},\"selector\":{\"id\":\"default\"}}],\"border\":[{\"properties\":{\"show\":{\"expr\":{\"Literal\":{\"Value\":\"false\"}}}},\"selector\":{\"id\":\"default\"}}]},\"vcObjects\":{\"background\":[{\"properties\":{\"show\":{\"expr\":{\"Literal\":{\"Value\":\"false\"}}}}}],\"padding\":[{\"properties\":{\"bottom\":{\"expr\":{\"Literal\":{\"Value\":\"0D\"}}},\"left\":{\"expr\":{\"Literal\":{\"Value\":\"0D\"}}},\"top\":{\"expr\":{\"Literal\":{\"Value\":\"0D\"}}},\"right\":{\"expr\":{\"Literal\":{\"Value\":\"0D\"}}}}}]}}}",
          "filters": "[]",
          "height": 120.20,
          "width": 992.29,
          "x": 265.97,
          "y": 23.02,
          "z": 0.00
        },
        {
          "config": "{\"name\":\"218adcd686a4526a33e4\",\"layouts\":[{\"id\":0,\"position\":{\"x\":23.04921968787515,\"y\":153.66146458583435,\"z\":6000,\"width\":213.58943577430972,\"height\":127.5390156062425,\"tabOrder\":6000}}],\"singleVisual\":{\"visualType\":\"cardVisual\",\"projections\":{\"Data\":[{\"queryRef\":\"Min(fact_steam_games_gl.name)\"}]},\"prototypeQuery\":{\"Version\":2,\"From\":[{\"Name\":\"f\",\"Entity\":\"fact_steam_games_gl\",\"Type\":0}],\"Select\":[{\"Aggregation\":{\"Expression\":{\"Column\":{\"Expression\":{\"SourceRef\":{\"Source\":\"f\"}},\"Property\":\"name\"}},\"Function\":3},\"Name\":\"Min(fact_steam_games_gl.name)\",\"NativeReferenceName\":\"First name\"}]},\"drillFilterOtherVisuals\":true,\"objects\":{\"layout\":[{\"properties\":{\"paddingUniform\":{\"expr\":{\"Literal\":{\"Value\":\"0L\"}}},\"backgroundShow\":{\"expr\":{\"Literal\":{\"Value\":\"false\"}}}},\"selector\":{\"id\":\"default\"}}],\"fillCustom\":[{\"properties\":{\"show\":{\"expr\":{\"Literal\":{\"Value\":\"false\"}}}}}],\"accentBar\":[{\"properties\":{\"show\":{\"expr\":{\"Literal\":{\"Value\":\"true\"}}},\"color\":{\"solid\":{\"color\":{\"expr\":{\"Literal\":{\"Value\":\"'#5F9EA0'\"}}}}},\"position\":{\"expr\":{\"Literal\":{\"Value\":\"'Top'\"}}},\"width\":{\"expr\":{\"Literal\":{\"Value\":\"13D\"}}}},\"selector\":{\"metadata\":\"Min(fact_steam_games_gl.name)\"}}],\"label\":[{\"properties\":{\"text\":{\"expr\":{\"Literal\":{\"Value\":\"'Top Game'\"}}},\"fontSize\":{\"expr\":{\"Literal\":{\"Value\":\"13D\"}}},\"bold\":{\"expr\":{\"Literal\":{\"Value\":\"true\"}}},\"position\":{\"expr\":{\"Literal\":{\"Value\":\"'aboveValue'\"}}}},\"selector\":{\"metadata\":\"Min(fact_steam_games_gl.name)\"}}],\"spacing\":[{\"properties\":{\"verticalSpacing\":{\"expr\":{\"Literal\":{\"Value\":\"6L\"}}}},\"selector\":{\"metadata\":\"Min(fact_steam_games_gl.name)\"}}],\"value\":[{\"properties\":{\"fontFamily\":{\"expr\":{\"Literal\":{\"Value\":\"'''Segoe UI Bold'', wf_segoe-ui_bold, helvetica, arial, sans-serif'\"}}},\"fontSize\":{\"expr\":{\"Literal\":{\"Value\":\"15D\"}}},\"textWrap\":{\"expr\":{\"Literal\":{\"Value\":\"true\"}}},\"horizontalAlignment\":{\"expr\":{\"Literal\":{\"Value\":\"'center'\"}}}},\"selector\":{\"metadata\":\"Min(fact_steam_games_gl.name)\"}},{\"properties\":{\"fontSize\":{\"expr\":{\"Literal\":{\"Value\":\"15D\"}}}},\"selector\":{\"id\":\"default\"}}],\"padding\":[{\"properties\":{\"paddingUniform\":{\"expr\":{\"Literal\":{\"Value\":\"7L\"}}}},\"selector\":{\"id\":\"default\"}}]},\"vcObjects\":{\"background\":[{\"properties\":{\"show\":{\"expr\":{\"Literal\":{\"Value\":\"false\"}}}}}],\"padding\":[{\"properties\":{\"top\":{\"expr\":{\"Literal\":{\"Value\":\"0D\"}}},\"left\":{\"expr\":{\"Literal\":{\"Value\":\"0D\"}}},\"bottom\":{\"expr\":{\"Literal\":{\"Value\":\"0D\"}}},\"right\":{\"expr\":{\"Literal\":{\"Value\":\"0D\"}}}}}],\"dropShadow\":[{\"properties\":{\"show\":{\"expr\":{\"Literal\":{\"Value\":\"true\"}}}}}]}}}",
          "filters": "[{\"name\":\"7254024efd790255421c\",\"expression\":{\"Column\":{\"Expression\":{\"SourceRef\":{\"Entity\":\"fact_steam_games_gl\"}},\"Property\":\"name\"}},\"filter\":{\"Version\":2,\"From\":[{\"Name\":\"subquery\",\"Expression\":{\"Subquery\":{\"Query\":{\"Version\":2,\"From\":[{\"Name\":\"f\",\"Entity\":\"fact_steam_games_gl\",\"Type\":0},{\"Name\":\"m\",\"Entity\":\"Measure Table\",\"Type\":0}],\"Select\":[{\"Column\":{\"Expression\":{\"SourceRef\":{\"Source\":\"f\"}},\"Property\":\"name\"},\"Name\":\"field\"}],\"OrderBy\":[{\"Direction\":2,\"Expression\":{\"Measure\":{\"Expression\":{\"SourceRef\":{\"Source\":\"m\"}},\"Property\":\"AVG Recommendations\"}}}],\"Top\":1}}},\"Type\":2},{\"Name\":\"f\",\"Entity\":\"fact_steam_games_gl\",\"Type\":0}],\"Where\":[{\"Condition\":{\"In\":{\"Expressions\":[{\"Column\":{\"Expression\":{\"SourceRef\":{\"Source\":\"f\"}},\"Property\":\"name\"}}],\"Table\":{\"SourceRef\":{\"Source\":\"subquery\"}}}}}]},\"type\":\"TopN\",\"howCreated\":1}]",
          "height": 127.54,
          "width": 213.59,
          "x": 23.05,
          "y": 153.66,
          "z": 6000.00
        },
        {
          "config": "{\"name\":\"33dd5f57f0d30f2d3002\",\"layouts\":[{\"id\":0,\"position\":{\"x\":23.04921968787515,\"y\":442.5450180072029,\"z\":8000,\"width\":213.58943577430972,\"height\":129.07563025210084,\"tabOrder\":8000}}],\"singleVisual\":{\"visualType\":\"cardVisual\",\"projections\":{\"Data\":[{\"queryRef\":\"Min(dim_categories_gl.category)\"}]},\"prototypeQuery\":{\"Version\":2,\"From\":[{\"Name\":\"d1\",\"Entity\":\"dim_categories_gl\",\"Type\":0}],\"Select\":[{\"Aggregation\":{\"Expression\":{\"Column\":{\"Expression\":{\"SourceRef\":{\"Source\":\"d1\"}},\"Property\":\"category\"}},\"Function\":3},\"Name\":\"Min(dim_categories_gl.category)\",\"NativeReferenceName\":\"First category\"}]},\"drillFilterOtherVisuals\":true,\"objects\":{\"layout\":[{\"properties\":{\"paddingUniform\":{\"expr\":{\"Literal\":{\"Value\":\"0L\"}}},\"backgroundShow\":{\"expr\":{\"Literal\":{\"Value\":\"false\"}}}},\"selector\":{\"id\":\"default\"}}],\"fillCustom\":[{\"properties\":{\"show\":{\"expr\":{\"Literal\":{\"Value\":\"false\"}}}}}],\"value\":[{\"properties\":{\"fontSize\":{\"expr\":{\"Literal\":{\"Value\":\"15D\"}}}},\"selector\":{\"id\":\"default\"}},{\"properties\":{\"bold\":{\"expr\":{\"Literal\":{\"Value\":\"false\"}}},\"fontFamily\":{\"expr\":{\"Literal\":{\"Value\":\"'''Segoe UI Bold'', wf_segoe-ui_bold, helvetica, arial, sans-serif'\"}}},\"textWrap\":{\"expr\":{\"Literal\":{\"Value\":\"true\"}}},\"horizontalAlignment\":{\"expr\":{\"Literal\":{\"Value\":\"'center'\"}}}},\"selector\":{\"metadata\":\"Min(dim_categories_gl.category)\"}}],\"accentBar\":[{\"properties\":{\"show\":{\"expr\":{\"Literal\":{\"Value\":\"true\"}}},\"position\":{\"expr\":{\"Literal\":{\"Value\":\"'Top'\"}}},\"color\":{\"solid\":{\"color\":{\"expr\":{\"Literal\":{\"Value\":\"'#5F9EA0'\"}}}}},\"width\":{\"expr\":{\"Literal\":{\"Value\":\"12D\"}}}},\"selector\":{\"id\":\"default\"}}],\"label\":[{\"properties\":{\"text\":{\"expr\":{\"Literal\":{\"Value\":\"'Top Category'\"}}},\"bold\":{\"expr\":{\"Literal\":{\"Value\":\"true\"}}},\"position\":{\"expr\":{\"Literal\":{\"Value\":\"'aboveValue'\"}}}},\"selector\":{\"metadata\":\"Min(dim_categories_gl.category)\"}}]},\"vcObjects\":{\"background\":[{\"properties\":{\"show\":{\"expr\":{\"Literal\":{\"Value\":\"false\"}}}}}],\"padding\":[{\"properties\":{\"top\":{\"expr\":{\"Literal\":{\"Value\":\"0D\"}}},\"left\":{\"expr\":{\"Literal\":{\"Value\":\"0D\"}}},\"bottom\":{\"expr\":{\"Literal\":{\"Value\":\"0D\"}}},\"right\":{\"expr\":{\"Literal\":{\"Value\":\"0D\"}}}}}],\"dropShadow\":[{\"properties\":{\"show\":{\"expr\":{\"Literal\":{\"Value\":\"true\"}}}}}]}}}",
          "filters": "[]",
          "height": 129.08,
          "width": 213.59,
          "x": 23.05,
          "y": 442.55,
          "z": 8000.00
        },
        {
          "config": "{\"name\":\"35944bb0d8efcf52ecb7\",\"layouts\":[{\"id\":0,\"position\":{\"x\":919.4005994005995,\"y\":522.997002997003,\"z\":5000,\"width\":324.7952047952048,\"height\":204.5954045954046,\"tabOrder\":5000}}],\"singleVisual\":{\"visualType\":\"tableEx\",\"projections\":{\"Values\":[{\"queryRef\":\"fact_steam_games_gl.name\"},{\"queryRef\":\"Measure Table.AVG Recommendations\"},{\"queryRef\":\"Measure Table.AVG Price\"}]},\"prototypeQuery\":{\"Version\":2,\"From\":[{\"Name\":\"f\",\"Entity\":\"fact_steam_games_gl\",\"Type\":0},{\"Name\":\"m\",\"Entity\":\"Measure Table\",\"Type\":0}],\"Select\":[{\"Column\":{\"Expression\":{\"SourceRef\":{\"Source\":\"f\"}},\"Property\":\"name\"},\"Name\":\"fact_steam_games_gl.name\",\"NativeReferenceName\":\"Top 100 Games\"},{\"Measure\":{\"Expression\":{\"SourceRef\":{\"Source\":\"m\"}},\"Property\":\"AVG Recommendations\"},\"Name\":\"Measure Table.AVG Recommendations\",\"NativeReferenceName\":\"Recommendations\"},{\"Measure\":{\"Expression\":{\"SourceRef\":{\"Source\":\"m\"}},\"Property\":\"AVG Price\"},\"Name\":\"Measure Table.AVG Price\",\"NativeReferenceName\":\"Price\"}],\"OrderBy\":[{\"Direction\":2,\"Expression\":{\"Measure\":{\"Expression\":{\"SourceRef\":{\"Source\":\"m\"}},\"Property\":\"AVG Recommendations\"}}}]},\"columnProperties\":{\"Measure Table.AVG Recommendations\":{\"formatString\":\"#,0\",\"displayName\":\"Recommendations\"},\"Measure Table.AVG Price\":{\"formatString\":\"\\\\$#,0.00;(\\\\$#,0.00);\\\\$#,0.00\",\"displayName\":\"Price\"},\"fact_steam_games_gl.name\":{\"displayName\":\"Top 100 Games\"}},\"drillFilterOtherVisuals\":true,\"objects\":{\"columnWidth\":[{\"properties\":{\"value\":{\"expr\":{\"Literal\":{\"Value\":\"100.98921158868492D\"}}}},\"selector\":{\"metadata\":\"fact_steam_games_gl.name\"}},{\"properties\":{\"value\":{\"expr\":{\"Literal\":{\"Value\":\"122.44255417733083D\"}}}},\"selector\":{\"metadata\":\"Measure Table.AVG Recommendations\"}},{\"properties\":{\"value\":{\"expr\":{\"Literal\":{\"Value\":\"78.5064935064935D\"}}}},\"selector\":{\"metadata\":\"Measure Table.AVG Price\"}}],\"columnHeaders\":[{\"properties\":{\"wordWrap\":{\"expr\":{\"Literal\":{\"Value\":\"false\"}}},\"alignment\":{\"expr\":{\"Literal\":{\"Value\":\"'Center'\"}}},\"bold\":{\"expr\":{\"Literal\":{\"Value\":\"true\"}}},\"fontSize\":{\"expr\":{\"Literal\":{\"Value\":\"9D\"}}}}}],\"columnFormatting\":[{\"properties\":{\"styleHeader\":{\"expr\":{\"Literal\":{\"Value\":\"false\"}}},\"dataBars\":{\"positiveColor\":{\"solid\":{\"color\":{\"expr\":{\"Literal\":{\"Value\":\"'#5F9EA0'\"}}}}},\"negativeColor\":{\"solid\":{\"color\":{\"expr\":{\"Literal\":{\"Value\":\"'minColor'\"}}}}},\"axisColor\":{\"solid\":{\"color\":{\"expr\":{\"Literal\":{\"Value\":\"'foreground'\"}}}}},\"reverseDirection\":{\"expr\":{\"Literal\":{\"Value\":\"false\"}}},\"hideText\":{\"expr\":{\"Literal\":{\"Value\":\"false\"}}},\"totalMatchingOption\":{\"expr\":{\"Literal\":{\"Value\":\"1L\"}}}}},\"selector\":{\"metadata\":\"Measure Table.AVG Recommendations\"}},{\"properties\":{\"dataBars\":{\"positiveColor\":{\"solid\":{\"color\":{\"expr\":{\"Literal\":{\"Value\":\"'#F08080'\"}}}}},\"negativeColor\":{\"solid\":{\"color\":{\"expr\":{\"Literal\":{\"Value\":\"'minColor'\"}}}}},\"axisColor\":{\"solid\":{\"color\":{\"expr\":{\"Literal\":{\"Value\":\"'foreground'\"}}}}},\"reverseDirection\":{\"expr\":{\"Literal\":{\"Value\":\"false\"}}},\"hideText\":{\"expr\":{\"Literal\":{\"Value\":\"false\"}}},\"totalMatchingOption\":{\"expr\":{\"Literal\":{\"Value\":\"1L\"}}}}},\"selector\":{\"metadata\":\"Measure Table.AVG Price\"}}],\"values\":[{\"properties\":{\"wordWrap\":{\"expr\":{\"Literal\":{\"Value\":\"false\"}}}}}]},\"vcObjects\":{\"background\":[{\"properties\":{\"show\":{\"expr\":{\"Literal\":{\"Value\":\"false\"}}}}}],\"stylePreset\":[{\"properties\":{\"name\":{\"expr\":{\"Literal\":{\"Value\":\"'None'\"}}}}}]}}}",
          "filters": "[{\"expression\":{\"Column\":{\"Expression\":{\"SourceRef\":{\"Entity\":\"fact_steam_games_gl\"}},\"Property\":\"name\"}},\"filter\":{\"Version\":2,\"From\":[{\"Name\":\"subquery\",\"Expression\":{\"Subquery\":{\"Query\":{\"Version\":2,\"From\":[{\"Name\":\"f\",\"Entity\":\"fact_steam_games_gl\",\"Type\":0},{\"Name\":\"m\",\"Entity\":\"Measure Table\",\"Type\":0}],\"Select\":[{\"Column\":{\"Expression\":{\"SourceRef\":{\"Source\":\"f\"}},\"Property\":\"name\"},\"Name\":\"field\"}],\"OrderBy\":[{\"Direction\":2,\"Expression\":{\"Measure\":{\"Expression\":{\"SourceRef\":{\"Source\":\"m\"}},\"Property\":\"AVG Recommendations\"}}}],\"Top\":100}}},\"Type\":2},{\"Name\":\"f\",\"Entity\":\"fact_steam_games_gl\",\"Type\":0}],\"Where\":[{\"Condition\":{\"In\":{\"Expressions\":[{\"Column\":{\"Expression\":{\"SourceRef\":{\"Source\":\"f\"}},\"Property\":\"name\"}}],\"Table\":{\"SourceRef\":{\"Source\":\"subquery\"}}}}}]},\"type\":\"TopN\",\"howCreated\":0,\"isHiddenInViewMode\":false}]",
          "height": 204.60,
          "width": 324.80,
          "x": 919.40,
          "y": 523.00,
          "z": 5000.00
        },
        {
          "config": "{\"name\":\"52fab7e575a724e49f08\",\"layouts\":[{\"id\":0,\"position\":{\"x\":265.0674846625767,\"y\":523.1595092024539,\"z\":4000,\"width\":654.5306748466257,\"height\":204.61349693251532,\"tabOrder\":4000}}],\"singleVisual\":{\"visualType\":\"treemap\",\"projections\":{\"Group\":[{\"queryRef\":\"dim_developers_gl.developer\",\"active\":true}],\"Values\":[{\"queryRef\":\"Measure Table.AVG Recommendations\"}]},\"prototypeQuery\":{\"Version\":2,\"From\":[{\"Name\":\"d\",\"Entity\":\"dim_developers_gl\",\"Type\":0},{\"Name\":\"m\",\"Entity\":\"Measure Table\",\"Type\":0}],\"Select\":[{\"Column\":{\"Expression\":{\"SourceRef\":{\"Source\":\"d\"}},\"Property\":\"developer\"},\"Name\":\"dim_developers_gl.developer\",\"NativeReferenceName\":\"developer\"},{\"Measure\":{\"Expression\":{\"SourceRef\":{\"Source\":\"m\"}},\"Property\":\"AVG Recommendations\"},\"Name\":\"Measure Table.AVG Recommendations\",\"NativeReferenceName\":\"AVG Recommendations\"}]},\"drillFilterOtherVisuals\":true,\"objects\":{\"dataPoint\":[{\"properties\":{\"fill\":{\"solid\":{\"color\":{\"expr\":{\"FillRule\":{\"Input\":{\"Measure\":{\"Expression\":{\"SourceRef\":{\"Entity\":\"Measure Table\"}},\"Property\":\"AVG Recommendations\"}},\"FillRule\":{\"linearGradient2\":{\"min\":{\"color\":{\"Literal\":{\"Value\":\"'minColor'\"}}},\"max\":{\"color\":{\"Literal\":{\"Value\":\"'#2E6B6D'\"}}},\"nullColoringStrategy\":{\"strategy\":{\"Literal\":{\"Value\":\"'asZero'\"}}}}}}}}}}},\"selector\":{\"data\":[{\"dataViewWildcard\":{\"matchingOption\":1}}]}},{\"properties\":{\"fill\":{\"solid\":{\"color\":{\"expr\":{\"ThemeDataColor\":{\"ColorId\":9,\"Percent\":0.6}}}}}},\"selector\":{\"data\":[{\"scopeId\":{\"Comparison\":{\"ComparisonKind\":0,\"Left\":{\"Column\":{\"Expression\":{\"SourceRef\":{\"Entity\":\"dim_developers_gl\"}},\"Property\":\"developer\"}},\"Right\":{\"Literal\":{\"Value\":\"'DICE'\"}}}}}]}},{\"properties\":{\"fill\":{\"solid\":{\"color\":{\"expr\":{\"Literal\":{\"Value\":\"'#F08080'\"}}}}}},\"selector\":{\"data\":[{\"scopeId\":{\"Comparison\":{\"ComparisonKind\":0,\"Left\":{\"Column\":{\"Expression\":{\"SourceRef\":{\"Entity\":\"dim_developers_gl\"}},\"Property\":\"developer\"}},\"Right\":{\"Literal\":{\"Value\":\"'Playground Games'\"}}}}}]}},{\"properties\":{\"fill\":{\"solid\":{\"color\":{\"expr\":{\"ThemeDataColor\":{\"ColorId\":3,\"Percent\":0.6}}}}}},\"selector\":{\"data\":[{\"scopeId\":{\"Comparison\":{\"ComparisonKind\":0,\"Left\":{\"Column\":{\"Expression\":{\"SourceRef\":{\"Entity\":\"dim_developers_gl\"}},\"Property\":\"developer\"}},\"Right\":{\"Literal\":{\"Value\":\"'24 Entertainment'\"}}}}}]}},{\"properties\":{\"fill\":{\"solid\":{\"color\":{\"expr\":{\"ThemeDataColor\":{\"ColorId\":5,\"Percent\":0.4}}}}}},\"selector\":{\"data\":[{\"scopeId\":{\"Comparison\":{\"ComparisonKind\":0,\"Left\":{\"Column\":{\"Expression\":{\"SourceRef\":{\"Entity\":\"dim_developers_gl\"}},\"Property\":\"developer\"}},\"Right\":{\"Literal\":{\"Value\":\"'Hazelight Studios'\"}}}}}]}},{\"properties\":{\"fill\":{\"solid\":{\"color\":{\"expr\":{\"Literal\":{\"Value\":\"'#579BD9'\"}}}}}},\"selector\":{\"data\":[{\"scopeId\":{\"Comparison\":{\"ComparisonKind\":0,\"Left\":{\"Column\":{\"Expression\":{\"SourceRef\":{\"Entity\":\"dim_developers_gl\"}},\"Property\":\"developer\"}},\"Right\":{\"Literal\":{\"Value\":\"'Hazelight Studio'\"}}}}}]}},{\"properties\":{\"fill\":{\"solid\":{\"color\":{\"expr\":{\"ThemeDataColor\":{\"ColorId\":9,\"Percent\":0.4}}}}}},\"selector\":{\"data\":[{\"scopeId\":{\"Comparison\":{\"ComparisonKind\":0,\"Left\":{\"Column\":{\"Expression\":{\"SourceRef\":{\"Entity\":\"dim_developers_gl\"}},\"Property\":\"developer\"}},\"Right\":{\"Literal\":{\"Value\":\"'Jetpack Interactive'\"}}}}}]}},{\"properties\":{\"fill\":{\"solid\":{\"color\":{\"expr\":{\"ThemeDataColor\":{\"ColorId\":3,\"Percent\":0.6}}}}}},\"selector\":{\"data\":[{\"scopeId\":{\"Comparison\":{\"ComparisonKind\":0,\"Left\":{\"Column\":{\"Expression\":{\"SourceRef\":{\"Entity\":\"dim_developers_gl\"}},\"Property\":\"developer\"}},\"Right\":{\"Literal\":{\"Value\":\"'Santa Monica Studio'\"}}}}}]}},{\"properties\":{\"fill\":{\"solid\":{\"color\":{\"expr\":{\"ThemeDataColor\":{\"ColorId\":7,\"Percent\":0.2}}}}}},\"selector\":{\"data\":[{\"scopeId\":{\"Comparison\":{\"ComparisonKind\":0,\"Left\":{\"Column\":{\"Expression\":{\"SourceRef\":{\"Entity\":\"dim_developers_gl\"}},\"Property\":\"developer\"}},\"Right\":{\"Literal\":{\"Value\":\"'KAGAMI Ⅱ WORKs'\"}}}}}]}},{\"properties\":{\"fill\":{\"solid\":{\"color\":{\"expr\":{\"ThemeDataColor\":{\"ColorId\":8,\"Percent\":0.6}}}}}},\"selector\":{\"data\":[{\"scopeId\":{\"Comparison\":{\"ComparisonKind\":0,\"Left\":{\"Column\":{\"Expression\":{\"SourceRef\":{\"Entity\":\"dim_developers_gl\"}},\"Property\":\"developer\"}},\"Right\":{\"Literal\":{\"Value\":\"'EA Canada & EA Romania'\"}}}}}]}},{\"properties\":{\"fill\":{\"solid\":{\"color\":{\"expr\":{\"ThemeDataColor\":{\"ColorId\":6,\"Percent\":0.6}}}}}},\"selector\":{\"data\":[{\"scopeId\":{\"Comparison\":{\"ComparisonKind\":0,\"Left\":{\"Column\":{\"Expression\":{\"SourceRef\":{\"Entity\":\"dim_developers_gl\"}},\"Property\":\"developer\"}},\"Right\":{\"Literal\":{\"Value\":\"'Duoyi Games'\"}}}}}]}},{\"properties\":{\"fill\":{\"solid\":{\"color\":{\"expr\":{\"Literal\":{\"Value\":\"'#B3E3C1'\"}}}}}},\"selector\":{\"data\":[{\"scopeId\":{\"Comparison\":{\"ComparisonKind\":0,\"Left\":{\"Column\":{\"Expression\":{\"SourceRef\":{\"Entity\":\"dim_developers_gl\"}},\"Property\":\"developer\"}},\"Right\":{\"Literal\":{\"Value\":\"'DashNet'\"}}}}}]}},{\"properties\":{\"fill\":{\"solid\":{\"color\":{\"expr\":{\"Literal\":{\"Value\":\"'#E2BE95'\"}}}}}},\"selector\":{\"data\":[{\"scopeId\":{\"Comparison\":{\"ComparisonKind\":0,\"Left\":{\"Column\":{\"Expression\":{\"SourceRef\":{\"Entity\":\"dim_developers_gl\"}},\"Property\":\"developer\"}},\"Right\":{\"Literal\":{\"Value\":\"'Orteil'\"}}}}}]}},{\"properties\":{\"fill\":{\"solid\":{\"color\":{\"expr\":{\"ThemeDataColor\":{\"ColorId\":2,\"Percent\":0}}}}}},\"selector\":{\"data\":[{\"scopeId\":{\"Comparison\":{\"ComparisonKind\":0,\"Left\":{\"Column\":{\"Expression\":{\"SourceRef\":{\"Entity\":\"dim_developers_gl\"}},\"Property\":\"developer\"}},\"Right\":{\"Literal\":{\"Value\":\"'Youthcat Studio'\"}}}}}]}},{\"properties\":{\"fill\":{\"solid\":{\"color\":{\"expr\":{\"Literal\":{\"Value\":\"'#CDDB82'\"}}}}}},\"selector\":{\"data\":[{\"scopeId\":{\"Comparison\":{\"ComparisonKind\":0,\"Left\":{\"Column\":{\"Expression\":{\"SourceRef\":{\"Entity\":\"dim_developers_gl\"}},\"Property\":\"developer\"}},\"Right\":{\"Literal\":{\"Value\":\"'Bend Studio'\"}}}}}]}},{\"properties\":{\"fill\":{\"solid\":{\"color\":{\"expr\":{\"ThemeDataColor\":{\"ColorId\":9,\"Percent\":-0.25}}}}}},\"selector\":{\"data\":[{\"scopeId\":{\"Comparison\":{\"ComparisonKind\":0,\"Left\":{\"Column\":{\"Expression\":{\"SourceRef\":{\"Entity\":\"dim_developers_gl\"}},\"Property\":\"developer\"}},\"Right\":{\"Literal\":{\"Value\":\"'Straight Back Games'\"}}}}}]}},{\"properties\":{\"fill\":{\"solid\":{\"color\":{\"expr\":{\"ThemeDataColor\":{\"ColorId\":1,\"Percent\":0.4}}}}}},\"selector\":{\"data\":[{\"scopeId\":{\"Comparison\":{\"ComparisonKind\":0,\"Left\":{\"Column\":{\"Expression\":{\"SourceRef\":{\"Entity\":\"dim_developers_gl\"}},\"Property\":\"developer\"}},\"Right\":{\"Literal\":{\"Value\":\"'Climax Studios'\"}}}}}]}},{\"properties\":{\"fill\":{\"solid\":{\"color\":{\"expr\":{\"ThemeDataColor\":{\"ColorId\":4,\"Percent\":0.6}}}}}},\"selector\":{\"data\":[{\"scopeId\":{\"Comparison\":{\"ComparisonKind\":0,\"Left\":{\"Column\":{\"Expression\":{\"SourceRef\":{\"Entity\":\"dim_developers_gl\"}},\"Property\":\"developer\"}},\"Right\":{\"Literal\":{\"Value\":\"'Forgotten Empires'\"}}}}}]}},{\"properties\":{\"fill\":{\"solid\":{\"color\":{\"expr\":{\"ThemeDataColor\":{\"ColorId\":8,\"Percent\":0.4}}}}}},\"selector\":{\"data\":[{\"scopeId\":{\"Comparison\":{\"ComparisonKind\":0,\"Left\":{\"Column\":{\"Expression\":{\"SourceRef\":{\"Entity\":\"dim_developers_gl\"}},\"Property\":\"developer\"}},\"Right\":{\"Literal\":{\"Value\":\"'Relic Entertainment'\"}}}}}]}},{\"properties\":{\"fill\":{\"solid\":{\"color\":{\"expr\":{\"ThemeDataColor\":{\"ColorId\":2,\"Percent\":0.6}}}}}},\"selector\":{\"data\":[{\"scopeId\":{\"Comparison\":{\"ComparisonKind\":0,\"Left\":{\"Column\":{\"Expression\":{\"SourceRef\":{\"Entity\":\"dim_developers_gl\"}},\"Property\":\"developer\"}},\"Right\":{\"Literal\":{\"Value\":\"'World''s Edge'\"}}}}}]}}]},\"vcObjects\":{\"title\":[{\"properties\":{\"show\":{\"expr\":{\"Literal\":{\"Value\":\"false\"}}}}}],\"background\":[{\"properties\":{\"show\":{\"expr\":{\"Literal\":{\"Value\":\"false\"}}}}}],\"visualTooltip\":[{\"properties\":{\"section\":{\"expr\":{\"Literal\":{\"Value\":\"'e0e31cbc79b4596b6b6b'\"}}}}}]}}}",
          "filters": "[{\"expression\":{\"Column\":{\"Expression\":{\"SourceRef\":{\"Entity\":\"dim_developers_gl\"}},\"Property\":\"developer\"}},\"filter\":{\"Version\":2,\"From\":[{\"Name\":\"subquery\",\"Expression\":{\"Subquery\":{\"Query\":{\"Version\":2,\"From\":[{\"Name\":\"d\",\"Entity\":\"dim_developers_gl\",\"Type\":0},{\"Name\":\"m\",\"Entity\":\"Measure Table\",\"Type\":0}],\"Select\":[{\"Column\":{\"Expression\":{\"SourceRef\":{\"Source\":\"d\"}},\"Property\":\"developer\"},\"Name\":\"field\"}],\"OrderBy\":[{\"Direction\":2,\"Expression\":{\"Measure\":{\"Expression\":{\"SourceRef\":{\"Source\":\"m\"}},\"Property\":\"AVG Recommendations\"}}}],\"Top\":20}}},\"Type\":2},{\"Name\":\"d\",\"Entity\":\"dim_developers_gl\",\"Type\":0}],\"Where\":[{\"Condition\":{\"In\":{\"Expressions\":[{\"Column\":{\"Expression\":{\"SourceRef\":{\"Source\":\"d\"}},\"Property\":\"developer\"}}],\"Table\":{\"SourceRef\":{\"Source\":\"subquery\"}}}}}]},\"type\":\"TopN\",\"howCreated\":0,\"isHiddenInViewMode\":false}]",
          "height": 204.61,
          "width": 654.53,
          "x": 265.07,
          "y": 523.16,
          "z": 4000.00
        },
        {
          "config": "{\"name\":\"61f87040cfba2013cbce\",\"layouts\":[{\"id\":0,\"position\":{\"x\":12.787212787212788,\"y\":3.8361638361638364,\"z\":11000,\"width\":223.7762237762238,\"height\":195.64435564435564,\"tabOrder\":11000}}],\"singleVisual\":{\"visualType\":\"shape\",\"drillFilterOtherVisuals\":true,\"objects\":{\"shape\":[{\"properties\":{\"tileShape\":{\"expr\":{\"Literal\":{\"Value\":\"'line'\"}}},\"linecapType\":{\"expr\":{\"Literal\":{\"Value\":\"'round'\"}}}}}],\"rotation\":[{\"properties\":{\"shapeAngle\":{\"expr\":{\"Literal\":{\"Value\":\"0L\"}}}}}],\"outline\":[{\"properties\":{\"show\":{\"expr\":{\"Literal\":{\"Value\":\"true\"}}}}},{\"properties\":{\"lineColor\":{\"solid\":{\"color\":{\"expr\":{\"Literal\":{\"Value\":\"'#5F9EA0'\"}}}}}},\"selector\":{\"id\":\"default\"}}],\"shadow\":[{\"properties\":{\"show\":{\"expr\":{\"Literal\":{\"Value\":\"true\"}}}}}],\"glow\":[{\"properties\":{\"show\":{\"expr\":{\"Literal\":{\"Value\":\"false\"}}}}}],\"fill\":[{\"properties\":{\"fillColor\":{\"solid\":{\"color\":{\"expr\":{\"Literal\":{\"Value\":\"'#5F9EA0'\"}}}}},\"transparency\":{\"expr\":{\"Literal\":{\"Value\":\"0D\"}}}},\"selector\":{\"id\":\"default\"}},{\"properties\":{\"show\":{\"expr\":{\"Literal\":{\"Value\":\"true\"}}}}}]},\"vcObjects\":{\"dropShadow\":[{\"properties\":{\"show\":{\"expr\":{\"Literal\":{\"Value\":\"false\"}}}}}]}},\"howCreated\":\"InsertVisualButton\"}",
          "filters": "[]",
          "height": 195.64,
          "width": 223.78,
          "x": 12.79,
          "y": 3.84,
          "z": 11000.00
        },
        {
          "config": "{\"name\":\"69691aa8048f251a53d1\",\"layouts\":[{\"id\":0,\"position\":{\"x\":283.6687116564417,\"y\":180.19938650306747,\"z\":2000,\"width\":466.19325153374234,\"height\":55.80368098159509,\"tabOrder\":2000}}],\"singleVisual\":{\"visualType\":\"slicer\",\"projections\":{\"Values\":[{\"queryRef\":\"metrics selection.metrics selection\",\"active\":true}]},\"prototypeQuery\":{\"Version\":2,\"From\":[{\"Name\":\"m\",\"Entity\":\"metrics selection\",\"Type\":0}],\"Select\":[{\"Column\":{\"Expression\":{\"SourceRef\":{\"Source\":\"m\"}},\"Property\":\"metrics selection\"},\"Name\":\"metrics selection.metrics selection\",\"NativeReferenceName\":\"metrics selection\"}]},\"columnProperties\":{\"metrics selection.metrics selection\":{\"formatString\":\"G\"}},\"drillFilterOtherVisuals\":true,\"objects\":{\"general\":[{\"properties\":{\"filter\":{\"filter\":{\"Version\":2,\"From\":[{\"Name\":\"m\",\"Entity\":\"metrics selection\",\"Type\":0}],\"Where\":[{\"Condition\":{\"In\":{\"Expressions\":[{\"Column\":{\"Expression\":{\"SourceRef\":{\"Source\":\"m\"}},\"Property\":\"metrics selection Fields\"}}],\"Values\":[[{\"Literal\":{\"Value\":\"'''Measure Table''[Total Games]'\"}}]]}}}]}}}}],\"data\":[{\"properties\":{\"mode\":{\"expr\":{\"Literal\":{\"Value\":\"'Dropdown'\"}}}}}],\"header\":[{\"properties\":{\"show\":{\"expr\":{\"Literal\":{\"Value\":\"false\"}}}}}]},\"vcObjects\":{\"title\":[{\"properties\":{\"show\":{\"expr\":{\"Literal\":{\"Value\":\"false\"}}}}}],\"padding\":[{\"properties\":{\"bottom\":{\"expr\":{\"Literal\":{\"Value\":\"0D\"}}},\"top\":{\"expr\":{\"Literal\":{\"Value\":\"0D\"}}},\"left\":{\"expr\":{\"Literal\":{\"Value\":\"0D\"}}},\"right\":{\"expr\":{\"Literal\":{\"Value\":\"0D\"}}}}}],\"background\":[{\"properties\":{\"show\":{\"expr\":{\"Literal\":{\"Value\":\"false\"}}}}}]},\"cachedFilterDisplayItems\":[{\"id\":{\"scopeId\":{\"Comparison\":{\"ComparisonKind\":0,\"Left\":{\"Column\":{\"Expression\":{\"SourceRef\":{\"Entity\":\"metrics selection\"}},\"Property\":\"metrics selection Fields\"}},\"Right\":{\"Literal\":{\"Value\":\"'''Measure Table''[Total Games]'\"}}}}},\"displayName\":\"Total Games\"}]}}",
          "filters": "[]",
          "height": 55.80,
          "width": 466.19,
          "x": 283.67,
          "y": 180.20,
          "z": 2000.00
        },
        {
          "config": "{\"name\":\"7bc6d97bbb4afe84ff0c\",\"layouts\":[{\"id\":0,\"position\":{\"x\":23.04921968787515,\"y\":585.4501800720288,\"z\":9000,\"width\":213.58943577430972,\"height\":127.5390156062425,\"tabOrder\":9000}}],\"singleVisual\":{\"visualType\":\"cardVisual\",\"projections\":{\"Data\":[{\"queryRef\":\"Min(dim_genres_gl.genre)\"}]},\"prototypeQuery\":{\"Version\":2,\"From\":[{\"Name\":\"d\",\"Entity\":\"dim_genres_gl\",\"Type\":0}],\"Select\":[{\"Aggregation\":{\"Expression\":{\"Column\":{\"Expression\":{\"SourceRef\":{\"Source\":\"d\"}},\"Property\":\"genre\"}},\"Function\":3},\"Name\":\"Min(dim_genres_gl.genre)\",\"NativeReferenceName\":\"First genre\"}]},\"drillFilterOtherVisuals\":true,\"objects\":{\"layout\":[{\"properties\":{\"paddingUniform\":{\"expr\":{\"Literal\":{\"Value\":\"0L\"}}},\"backgroundShow\":{\"expr\":{\"Literal\":{\"Value\":\"false\"}}}},\"selector\":{\"id\":\"default\"}}],\"fillCustom\":[{\"properties\":{\"show\":{\"expr\":{\"Literal\":{\"Value\":\"false\"}}}}}],\"value\":[{\"properties\":{\"fontSize\":{\"expr\":{\"Literal\":{\"Value\":\"20D\"}}},\"fontFamily\":{\"expr\":{\"Literal\":{\"Value\":\"'''Segoe UI Bold'', wf_segoe-ui_bold, helvetica, arial, sans-serif'\"}}}},\"selector\":{\"id\":\"default\"}},{\"properties\":{\"horizontalAlignment\":{\"expr\":{\"Literal\":{\"Value\":\"'center'\"}}},\"textWrap\":{\"expr\":{\"Literal\":{\"Value\":\"true\"}}},\"fontSize\":{\"expr\":{\"Literal\":{\"Value\":\"15D\"}}}},\"selector\":{\"metadata\":\"Min(dim_genres_gl.genre)\"}}],\"accentBar\":[{\"properties\":{\"show\":{\"expr\":{\"Literal\":{\"Value\":\"true\"}}},\"position\":{\"expr\":{\"Literal\":{\"Value\":\"'Top'\"}}},\"color\":{\"solid\":{\"color\":{\"expr\":{\"Literal\":{\"Value\":\"'#5F9EA0'\"}}}}},\"width\":{\"expr\":{\"Literal\":{\"Value\":\"12D\"}}}},\"selector\":{\"id\":\"default\"}}],\"label\":[{\"properties\":{\"text\":{\"expr\":{\"Literal\":{\"Value\":\"'Top Genre'\"}}},\"bold\":{\"expr\":{\"Literal\":{\"Value\":\"true\"}}},\"position\":{\"expr\":{\"Literal\":{\"Value\":\"'aboveValue'\"}}},\"textWrap\":{\"expr\":{\"Literal\":{\"Value\":\"false\"}}}},\"selector\":{\"metadata\":\"Min(dim_genres_gl.genre)\"}}]},\"vcObjects\":{\"background\":[{\"properties\":{\"show\":{\"expr\":{\"Literal\":{\"Value\":\"false\"}}}}}],\"padding\":[{\"properties\":{\"top\":{\"expr\":{\"Literal\":{\"Value\":\"0D\"}}},\"left\":{\"expr\":{\"Literal\":{\"Value\":\"0D\"}}},\"bottom\":{\"expr\":{\"Literal\":{\"Value\":\"0D\"}}},\"right\":{\"expr\":{\"Literal\":{\"Value\":\"0D\"}}}}}],\"dropShadow\":[{\"properties\":{\"show\":{\"expr\":{\"Literal\":{\"Value\":\"true\"}}}}}]}}}",
          "filters": "[{\"name\":\"b72dc746574dd0cf528d\",\"expression\":{\"Column\":{\"Expression\":{\"SourceRef\":{\"Entity\":\"dim_genres_gl\"}},\"Property\":\"genre\"}},\"filter\":{\"Version\":2,\"From\":[{\"Name\":\"subquery\",\"Expression\":{\"Subquery\":{\"Query\":{\"Version\":2,\"From\":[{\"Name\":\"d\",\"Entity\":\"dim_genres_gl\",\"Type\":0},{\"Name\":\"m\",\"Entity\":\"Measure Table\",\"Type\":0}],\"Select\":[{\"Column\":{\"Expression\":{\"SourceRef\":{\"Source\":\"d\"}},\"Property\":\"genre\"},\"Name\":\"field\"}],\"OrderBy\":[{\"Direction\":2,\"Expression\":{\"Measure\":{\"Expression\":{\"SourceRef\":{\"Source\":\"m\"}},\"Property\":\"AVG Recommendations\"}}}],\"Top\":1}}},\"Type\":2},{\"Name\":\"d\",\"Entity\":\"dim_genres_gl\",\"Type\":0}],\"Where\":[{\"Condition\":{\"In\":{\"Expressions\":[{\"Column\":{\"Expression\":{\"SourceRef\":{\"Source\":\"d\"}},\"Property\":\"genre\"}}],\"Table\":{\"SourceRef\":{\"Source\":\"subquery\"}}}}}]},\"type\":\"TopN\",\"howCreated\":1}]",
          "height": 127.54,
          "width": 213.59,
          "x": 23.05,
          "y": 585.45,
          "z": 9000.00
        },
        {
          "config": "{\"name\":\"92029b35aea6279adffe\",\"layouts\":[{\"id\":0,\"position\":{\"x\":23.01698301698302,\"y\":23.01698301698302,\"z\":10000,\"width\":213.54645354645356,\"height\":86.95304695304696,\"tabOrder\":10000}}],\"singleVisual\":{\"visualType\":\"textbox\",\"drillFilterOtherVisuals\":true,\"objects\":{\"general\":[{\"properties\":{\"paragraphs\":[{\"textRuns\":[{\"value\":\"\"}]}]}}]},\"vcObjects\":{\"background\":[{\"properties\":{\"show\":{\"expr\":{\"Literal\":{\"Value\":\"false\"}}}}}],\"title\":[{\"properties\":{\"show\":{\"expr\":{\"Literal\":{\"Value\":\"true\"}}},\"text\":{\"expr\":{\"Literal\":{\"Value\":\"'Steam Games Analysis Report'\"}}},\"fontFamily\":{\"expr\":{\"Literal\":{\"Value\":\"'''Segoe UI Bold'', wf_segoe-ui_bold, helvetica, arial, sans-serif'\"}}},\"fontSize\":{\"expr\":{\"Literal\":{\"Value\":\"20D\"}}},\"fontColor\":{\"solid\":{\"color\":{\"expr\":{\"Literal\":{\"Value\":\"'#5F9EA0'\"}}}}},\"bold\":{\"expr\":{\"Literal\":{\"Value\":\"true\"}}}}}],\"dropShadow\":[{\"properties\":{\"show\":{\"expr\":{\"Literal\":{\"Value\":\"false\"}}}}}]}}}",
          "filters": "[]",
          "height": 86.95,
          "width": 213.55,
          "x": 23.02,
          "y": 23.02,
          "z": 10000.00
        },
        {
          "config": "{\"name\":\"94b6f370084fa9100a20\",\"layouts\":[{\"id\":0,\"position\":{\"x\":274.3680981595092,\"y\":208.10122699386503,\"z\":1000,\"width\":475.49386503067484,\"height\":279.0184049079754,\"tabOrder\":1000}}],\"singleVisual\":{\"visualType\":\"clusteredBarChart\",\"projections\":{\"Y\":[{\"queryRef\":\"Measure Table.Total Games\"}],\"Category\":[{\"queryRef\":\"dim_genres_gl.genre\",\"active\":true}]},\"prototypeQuery\":{\"Version\":2,\"From\":[{\"Name\":\"d1\",\"Entity\":\"dim_genres_gl\",\"Type\":0},{\"Name\":\"m\",\"Entity\":\"Measure Table\",\"Type\":0}],\"Select\":[{\"Column\":{\"Expression\":{\"SourceRef\":{\"Source\":\"d1\"}},\"Property\":\"genre\"},\"Name\":\"dim_genres_gl.genre\",\"NativeReferenceName\":\"genre\"},{\"Measure\":{\"Expression\":{\"SourceRef\":{\"Source\":\"m\"}},\"Property\":\"Total Games\"},\"Name\":\"Measure Table.Total Games\",\"NativeReferenceName\":\"Total Games\"}],\"OrderBy\":[{\"Direction\":2,\"Expression\":{\"Measure\":{\"Expression\":{\"SourceRef\":{\"Source\":\"m\"}},\"Property\":\"Total Games\"}}}]},\"queryFieldParametersByRole\":{\"Y\":[{\"index\":0,\"length\":1,\"expr\":{\"Column\":{\"Expression\":{\"SourceRef\":{\"Entity\":\"metrics selection\"}},\"Property\":\"metrics selection\"}}}]},\"columnProperties\":{\"Measure Table.Total Games\":{\"displayName\":\"Total Games\"}},\"drillFilterOtherVisuals\":true,\"hasDefaultSort\":true,\"objects\":{\"categoryAxis\":[{\"properties\":{\"showAxisTitle\":{\"expr\":{\"Literal\":{\"Value\":\"false\"}}},\"switchAxisPosition\":{\"expr\":{\"Literal\":{\"Value\":\"false\"}}},\"concatenateLabels\":{\"expr\":{\"Literal\":{\"Value\":\"false\"}}},\"preferredCategoryWidth\":{\"expr\":{\"Literal\":{\"Value\":\"26D\"}}},\"show\":{\"expr\":{\"Literal\":{\"Value\":\"true\"}}},\"maxMarginFactor\":{\"expr\":{\"Literal\":{\"Value\":\"16L\"}}}}}],\"valueAxis\":[{\"properties\":{\"showAxisTitle\":{\"expr\":{\"Literal\":{\"Value\":\"false\"}}}}}],\"dataPoint\":[{\"properties\":{\"fill\":{\"solid\":{\"color\":{\"expr\":{\"Literal\":{\"Value\":\"'#5F9EA0'\"}}}}}},\"selector\":{\"data\":[{\"scopeId\":{\"Comparison\":{\"ComparisonKind\":0,\"Left\":{\"Column\":{\"Expression\":{\"SourceRef\":{\"Entity\":\"dim_genres_gl\"}},\"Property\":\"genre\"}},\"Right\":{\"Literal\":{\"Value\":\"'Action'\"}}}}}]}},{\"properties\":{\"fill\":{\"solid\":{\"color\":{\"expr\":{\"Literal\":{\"Value\":\"'#87CEEB'\"}}}}}},\"selector\":{\"data\":[{\"scopeId\":{\"Comparison\":{\"ComparisonKind\":0,\"Left\":{\"Column\":{\"Expression\":{\"SourceRef\":{\"Entity\":\"dim_genres_gl\"}},\"Property\":\"genre\"}},\"Right\":{\"Literal\":{\"Value\":\"'Simulation'\"}}}}}]}},{\"properties\":{\"fill\":{\"solid\":{\"color\":{\"expr\":{\"Literal\":{\"Value\":\"'#B0E0E6'\"}}}}}},\"selector\":{\"data\":[{\"scopeId\":{\"Comparison\":{\"ComparisonKind\":0,\"Left\":{\"Column\":{\"Expression\":{\"SourceRef\":{\"Entity\":\"dim_genres_gl\"}},\"Property\":\"genre\"}},\"Right\":{\"Literal\":{\"Value\":\"'Adventure'\"}}}}}]}},{\"properties\":{\"fill\":{\"solid\":{\"color\":{\"expr\":{\"Literal\":{\"Value\":\"'#F08080'\"}}}}}},\"selector\":{\"data\":[{\"scopeId\":{\"Comparison\":{\"ComparisonKind\":0,\"Left\":{\"Column\":{\"Expression\":{\"SourceRef\":{\"Entity\":\"dim_genres_gl\"}},\"Property\":\"genre\"}},\"Right\":{\"Literal\":{\"Value\":\"'Indie'\"}}}}}]}},{\"properties\":{\"fill\":{\"solid\":{\"color\":{\"expr\":{\"Literal\":{\"Value\":\"'#FFB6C1'\"}}}}}},\"selector\":{\"data\":[{\"scopeId\":{\"Comparison\":{\"ComparisonKind\":0,\"Left\":{\"Column\":{\"Expression\":{\"SourceRef\":{\"Entity\":\"dim_genres_gl\"}},\"Property\":\"genre\"}},\"Right\":{\"Literal\":{\"Value\":\"'Casual'\"}}}}}]}},{\"properties\":{\"fill\":{\"solid\":{\"color\":{\"expr\":{\"ThemeDataColor\":{\"ColorId\":2,\"Percent\":0.2}}}}}},\"selector\":{\"data\":[{\"scopeId\":{\"Comparison\":{\"ComparisonKind\":0,\"Left\":{\"Column\":{\"Expression\":{\"SourceRef\":{\"Entity\":\"dim_genres_gl\"}},\"Property\":\"genre\"}},\"Right\":{\"Literal\":{\"Value\":\"'Strategy'\"}}}}}]}},{\"properties\":{\"fill\":{\"solid\":{\"color\":{\"expr\":{\"ThemeDataColor\":{\"ColorId\":6,\"Percent\":0.4}}}}}},\"selector\":{\"data\":[{\"scopeId\":{\"Comparison\":{\"ComparisonKind\":0,\"Left\":{\"Column\":{\"Expression\":{\"SourceRef\":{\"Entity\":\"dim_genres_gl\"}},\"Property\":\"genre\"}},\"Right\":{\"Literal\":{\"Value\":\"'RPG'\"}}}}}]}},{\"properties\":{\"fill\":{\"solid\":{\"color\":{\"expr\":{\"Literal\":{\"Value\":\"'#DDA0DD'\"}}}}}},\"selector\":{\"data\":[{\"scopeId\":{\"Comparison\":{\"ComparisonKind\":0,\"Left\":{\"Column\":{\"Expression\":{\"SourceRef\":{\"Entity\":\"dim_genres_gl\"}},\"Property\":\"genre\"}},\"Right\":{\"Literal\":{\"Value\":\"'Free To Play'\"}}}}}]}},{\"properties\":{\"fill\":{\"solid\":{\"color\":{\"expr\":{\"ThemeDataColor\":{\"ColorId\":8,\"Percent\":0.6}}}}}},\"selector\":{\"data\":[{\"scopeId\":{\"Comparison\":{\"ComparisonKind\":0,\"Left\":{\"Column\":{\"Expression\":{\"SourceRef\":{\"Entity\":\"dim_genres_gl\"}},\"Property\":\"genre\"}},\"Right\":{\"Literal\":{\"Value\":\"'Early Access'\"}}}}}]}},{\"properties\":{\"fill\":{\"solid\":{\"color\":{\"expr\":{\"ThemeDataColor\":{\"ColorId\":3,\"Percent\":0.4}}}}}},\"selector\":{\"data\":[{\"scopeId\":{\"Comparison\":{\"ComparisonKind\":0,\"Left\":{\"Column\":{\"Expression\":{\"SourceRef\":{\"Entity\":\"dim_genres_gl\"}},\"Property\":\"genre\"}},\"Right\":{\"Literal\":{\"Value\":\"'Sports'\"}}}}}]}},{\"properties\":{\"fill\":{\"solid\":{\"color\":{\"expr\":{\"Literal\":{\"Value\":\"'#92D195'\"}}}}}},\"selector\":{\"data\":[{\"scopeId\":{\"Comparison\":{\"ComparisonKind\":0,\"Left\":{\"Column\":{\"Expression\":{\"SourceRef\":{\"Entity\":\"dim_genres_gl\"}},\"Property\":\"genre\"}},\"Right\":{\"Literal\":{\"Value\":\"'Racing'\"}}}}}]}},{\"properties\":{\"fill\":{\"solid\":{\"color\":{\"expr\":{\"ThemeDataColor\":{\"ColorId\":4,\"Percent\":0.4}}}}}},\"selector\":{\"data\":[{\"scopeId\":{\"Comparison\":{\"ComparisonKind\":0,\"Left\":{\"Column\":{\"Expression\":{\"SourceRef\":{\"Entity\":\"dim_genres_gl\"}},\"Property\":\"genre\"}},\"Right\":{\"Literal\":{\"Value\":\"'Massively Multiplayer'\"}}}}}]}},{\"properties\":{\"fill\":{\"solid\":{\"color\":{\"expr\":{\"ThemeDataColor\":{\"ColorId\":0,\"Percent\":-0.3}}}}}},\"selector\":{\"data\":[{\"scopeId\":{\"Comparison\":{\"ComparisonKind\":0,\"Left\":{\"Column\":{\"Expression\":{\"SourceRef\":{\"Entity\":\"dim_genres_gl\"}},\"Property\":\"genre\"}},\"Right\":{\"Literal\":{\"Value\":\"'Unknown'\"}}}}}]}},{\"properties\":{\"fill\":{\"solid\":{\"color\":{\"expr\":{\"ThemeDataColor\":{\"ColorId\":4,\"Percent\":-0.25}}}}}},\"selector\":{\"data\":[{\"scopeId\":{\"Comparison\":{\"ComparisonKind\":0,\"Left\":{\"Column\":{\"Expression\":{\"SourceRef\":{\"Entity\":\"dim_genres_gl\"}},\"Property\":\"genre\"}},\"Right\":{\"Literal\":{\"Value\":\"'Education'\"}}}}}]}},{\"properties\":{\"fill\":{\"solid\":{\"color\":{\"expr\":{\"ThemeDataColor\":{\"ColorId\":2,\"Percent\":-0.5}}}}}},\"selector\":{\"data\":[{\"scopeId\":{\"Comparison\":{\"ComparisonKind\":0,\"Left\":{\"Column\":{\"Expression\":{\"SourceRef\":{\"Entity\":\"dim_genres_gl\"}},\"Property\":\"genre\"}},\"Right\":{\"Literal\":{\"Value\":\"'Game Development'\"}}}}}]}},{\"properties\":{\"fill\":{\"solid\":{\"color\":{\"expr\":{\"ThemeDataColor\":{\"ColorId\":5,\"Percent\":0.4}}}}}},\"selector\":{\"data\":[{\"scopeId\":{\"Comparison\":{\"ComparisonKind\":0,\"Left\":{\"Column\":{\"Expression\":{\"SourceRef\":{\"Entity\":\"dim_genres_gl\"}},\"Property\":\"genre\"}},\"Right\":{\"Literal\":{\"Value\":\"'Animation & Modeling'\"}}}}}]}},{\"properties\":{\"fill\":{\"solid\":{\"color\":{\"expr\":{\"ThemeDataColor\":{\"ColorId\":2,\"Percent\":-0.25}}}}}},\"selector\":{\"data\":[{\"scopeId\":{\"Comparison\":{\"ComparisonKind\":0,\"Left\":{\"Column\":{\"Expression\":{\"SourceRef\":{\"Entity\":\"dim_genres_gl\"}},\"Property\":\"genre\"}},\"Right\":{\"Literal\":{\"Value\":\"'Design & Illustration'\"}}}}}]}},{\"properties\":{\"fill\":{\"solid\":{\"color\":{\"expr\":{\"ThemeDataColor\":{\"ColorId\":9,\"Percent\":-0.5}}}}}},\"selector\":{\"data\":[{\"scopeId\":{\"Comparison\":{\"ComparisonKind\":0,\"Left\":{\"Column\":{\"Expression\":{\"SourceRef\":{\"Entity\":\"dim_genres_gl\"}},\"Property\":\"genre\"}},\"Right\":{\"Literal\":{\"Value\":\"'Software Training'\"}}}}}]}},{\"properties\":{\"fill\":{\"solid\":{\"color\":{\"expr\":{\"ThemeDataColor\":{\"ColorId\":3,\"Percent\":0.6}}}}}},\"selector\":{\"data\":[{\"scopeId\":{\"Comparison\":{\"ComparisonKind\":0,\"Left\":{\"Column\":{\"Expression\":{\"SourceRef\":{\"Entity\":\"dim_genres_gl\"}},\"Property\":\"genre\"}},\"Right\":{\"Literal\":{\"Value\":\"'Utilities'\"}}}}}]}},{\"properties\":{\"fill\":{\"solid\":{\"color\":{\"expr\":{\"ThemeDataColor\":{\"ColorId\":4,\"Percent\":0}}}}}},\"selector\":{\"data\":[{\"scopeId\":{\"Comparison\":{\"ComparisonKind\":0,\"Left\":{\"Column\":{\"Expression\":{\"SourceRef\":{\"Entity\":\"dim_genres_gl\"}},\"Property\":\"genre\"}},\"Right\":{\"Literal\":{\"Value\":\"'Accounting'\"}}}}}]}},{\"properties\":{\"fill\":{\"solid\":{\"color\":{\"expr\":{\"Literal\":{\"Value\":\"'#579BD9'\"}}}}}},\"selector\":{\"data\":[{\"scopeId\":{\"Comparison\":{\"ComparisonKind\":0,\"Left\":{\"Column\":{\"Expression\":{\"SourceRef\":{\"Entity\":\"dim_genres_gl\"}},\"Property\":\"genre\"}},\"Right\":{\"Literal\":{\"Value\":\"'Video Production'\"}}}}}]}}]},\"vcObjects\":{\"title\":[{\"properties\":{\"show\":{\"expr\":{\"Literal\":{\"Value\":\"false\"}}}}}],\"background\":[{\"properties\":{\"show\":{\"expr\":{\"Literal\":{\"Value\":\"false\"}}}}}]}}}",
          "filters": "[]",
          "height": 279.02,
          "width": 475.49,
          "x": 274.37,
          "y": 208.10,
          "z": 1000.00
        },
        {
          "config": "{\"name\":\"b1dae98ddf81f155f200\",\"layouts\":[{\"id\":0,\"position\":{\"x\":23.04921968787515,\"y\":298.1032412965186,\"z\":7000,\"width\":213.58943577430972,\"height\":129.07563025210084,\"tabOrder\":7000}}],\"singleVisual\":{\"visualType\":\"cardVisual\",\"projections\":{\"Data\":[{\"queryRef\":\"Min(dim_developers_gl.developer)\"}]},\"prototypeQuery\":{\"Version\":2,\"From\":[{\"Name\":\"d\",\"Entity\":\"dim_developers_gl\",\"Type\":0}],\"Select\":[{\"Aggregation\":{\"Expression\":{\"Column\":{\"Expression\":{\"SourceRef\":{\"Source\":\"d\"}},\"Property\":\"developer\"}},\"Function\":3},\"Name\":\"Min(dim_developers_gl.developer)\",\"NativeReferenceName\":\"First developer\"}]},\"drillFilterOtherVisuals\":true,\"objects\":{\"layout\":[{\"properties\":{\"paddingUniform\":{\"expr\":{\"Literal\":{\"Value\":\"0L\"}}},\"backgroundShow\":{\"expr\":{\"Literal\":{\"Value\":\"false\"}}}},\"selector\":{\"id\":\"default\"}}],\"fillCustom\":[{\"properties\":{\"show\":{\"expr\":{\"Literal\":{\"Value\":\"false\"}}}}}],\"padding\":[{\"properties\":{\"paddingUniform\":{\"expr\":{\"Literal\":{\"Value\":\"7L\"}}}},\"selector\":{\"metadata\":\"Min(dim_developers_gl.developer)\"}}],\"accentBar\":[{\"properties\":{\"show\":{\"expr\":{\"Literal\":{\"Value\":\"true\"}}},\"color\":{\"solid\":{\"color\":{\"expr\":{\"Literal\":{\"Value\":\"'#5F9EA0'\"}}}}},\"position\":{\"expr\":{\"Literal\":{\"Value\":\"'Top'\"}}},\"width\":{\"expr\":{\"Literal\":{\"Value\":\"13D\"}}}},\"selector\":{\"metadata\":\"Min(dim_developers_gl.developer)\"}}],\"label\":[{\"properties\":{\"text\":{\"expr\":{\"Literal\":{\"Value\":\"'Top Developer'\"}}},\"bold\":{\"expr\":{\"Literal\":{\"Value\":\"true\"}}},\"position\":{\"expr\":{\"Literal\":{\"Value\":\"'aboveValue'\"}}}},\"selector\":{\"metadata\":\"Min(dim_developers_gl.developer)\"}}],\"spacing\":[{\"properties\":{\"verticalSpacing\":{\"expr\":{\"Literal\":{\"Value\":\"4L\"}}}},\"selector\":{\"metadata\":\"Min(dim_developers_gl.developer)\"}}],\"value\":[{\"properties\":{\"fontFamily\":{\"expr\":{\"Literal\":{\"Value\":\"'''Segoe UI Bold'', wf_segoe-ui_bold, helvetica, arial, sans-serif'\"}}},\"textWrap\":{\"expr\":{\"Literal\":{\"Value\":\"true\"}}},\"fontSize\":{\"expr\":{\"Literal\":{\"Value\":\"15D\"}}},\"horizontalAlignment\":{\"expr\":{\"Literal\":{\"Value\":\"'center'\"}}}},\"selector\":{\"metadata\":\"Min(dim_developers_gl.developer)\"}},{\"properties\":{\"fontSize\":{\"expr\":{\"Literal\":{\"Value\":\"15D\"}}}},\"selector\":{\"id\":\"default\"}}]},\"vcObjects\":{\"background\":[{\"properties\":{\"show\":{\"expr\":{\"Literal\":{\"Value\":\"false\"}}}}}],\"padding\":[{\"properties\":{\"top\":{\"expr\":{\"Literal\":{\"Value\":\"0D\"}}},\"left\":{\"expr\":{\"Literal\":{\"Value\":\"0D\"}}},\"bottom\":{\"expr\":{\"Literal\":{\"Value\":\"0D\"}}},\"right\":{\"expr\":{\"Literal\":{\"Value\":\"0D\"}}}}}],\"dropShadow\":[{\"properties\":{\"show\":{\"expr\":{\"Literal\":{\"Value\":\"true\"}}}}}]}}}",
          "filters": "[{\"name\":\"5553320c4df6396eef74\",\"expression\":{\"Column\":{\"Expression\":{\"SourceRef\":{\"Entity\":\"dim_developers_gl\"}},\"Property\":\"developer\"}},\"filter\":{\"Version\":2,\"From\":[{\"Name\":\"subquery\",\"Expression\":{\"Subquery\":{\"Query\":{\"Version\":2,\"From\":[{\"Name\":\"d\",\"Entity\":\"dim_developers_gl\",\"Type\":0},{\"Name\":\"m\",\"Entity\":\"Measure Table\",\"Type\":0}],\"Select\":[{\"Column\":{\"Expression\":{\"SourceRef\":{\"Source\":\"d\"}},\"Property\":\"developer\"},\"Name\":\"field\"}],\"OrderBy\":[{\"Direction\":2,\"Expression\":{\"Measure\":{\"Expression\":{\"SourceRef\":{\"Source\":\"m\"}},\"Property\":\"AVG Recommendations\"}}}],\"Top\":1}}},\"Type\":2},{\"Name\":\"d\",\"Entity\":\"dim_developers_gl\",\"Type\":0}],\"Where\":[{\"Condition\":{\"In\":{\"Expressions\":[{\"Column\":{\"Expression\":{\"SourceRef\":{\"Source\":\"d\"}},\"Property\":\"developer\"}}],\"Table\":{\"SourceRef\":{\"Source\":\"subquery\"}}}}}]},\"type\":\"TopN\",\"howCreated\":1}]",
          "height": 129.08,
          "width": 213.59,
          "x": 23.05,
          "y": 298.10,
          "z": 7000.00
        },
        {
          "config": "{\"name\":\"c465969a8560ef5ac6d6\",\"layouts\":[{\"id\":0,\"position\":{\"x\":762.1178821178821,\"y\":195.64435564435564,\"z\":3000,\"width\":482.0779220779221,\"height\":291.54845154845157,\"tabOrder\":3000}}],\"singleVisual\":{\"visualType\":\"areaChart\",\"projections\":{\"Y\":[{\"queryRef\":\"Measure Table.Total Games\"}],\"Category\":[{\"queryRef\":\"Date_Table.Date Hierarchy.Year\"},{\"queryRef\":\"Date_Table.Date Hierarchy.Quarter\"},{\"queryRef\":\"Date_Table.Date Hierarchy.StartOfMonth\",\"active\":true},{\"queryRef\":\"Date_Table.Date Hierarchy.Date\"}]},\"prototypeQuery\":{\"Version\":2,\"From\":[{\"Name\":\"d\",\"Entity\":\"Date_Table\",\"Type\":0},{\"Name\":\"m\",\"Entity\":\"Measure Table\",\"Type\":0}],\"Select\":[{\"HierarchyLevel\":{\"Expression\":{\"Hierarchy\":{\"Expression\":{\"SourceRef\":{\"Source\":\"d\"}},\"Hierarchy\":\"Date Hierarchy\"}},\"Level\":\"Year\"},\"Name\":\"Date_Table.Date Hierarchy.Year\",\"NativeReferenceName\":\"Date Hierarchy Year\"},{\"HierarchyLevel\":{\"Expression\":{\"Hierarchy\":{\"Expression\":{\"SourceRef\":{\"Source\":\"d\"}},\"Hierarchy\":\"Date Hierarchy\"}},\"Level\":\"Quarter\"},\"Name\":\"Date_Table.Date Hierarchy.Quarter\",\"NativeReferenceName\":\"Date Hierarchy Quarter\"},{\"HierarchyLevel\":{\"Expression\":{\"Hierarchy\":{\"Expression\":{\"SourceRef\":{\"Source\":\"d\"}},\"Hierarchy\":\"Date Hierarchy\"}},\"Level\":\"StartOfMonth\"},\"Name\":\"Date_Table.Date Hierarchy.StartOfMonth\",\"NativeReferenceName\":\"Date Hierarchy StartOfMonth\"},{\"HierarchyLevel\":{\"Expression\":{\"Hierarchy\":{\"Expression\":{\"SourceRef\":{\"Source\":\"d\"}},\"Hierarchy\":\"Date Hierarchy\"}},\"Level\":\"Date\"},\"Name\":\"Date_Table.Date Hierarchy.Date\",\"NativeReferenceName\":\"Date Hierarchy Date\"},{\"Measure\":{\"Expression\":{\"SourceRef\":{\"Source\":\"m\"}},\"Property\":\"Total Games\"},\"Name\":\"Measure Table.Total Games\",\"NativeReferenceName\":\"Total Games\"}],\"OrderBy\":[{\"Direction\":1,\"Expression\":{\"HierarchyLevel\":{\"Expression\":{\"Hierarchy\":{\"Expression\":{\"SourceRef\":{\"Source\":\"d\"}},\"Hierarchy\":\"Date Hierarchy\"}},\"Level\":\"Year\"}}}]},\"queryFieldParametersByRole\":{\"Y\":[{\"index\":0,\"length\":1,\"expr\":{\"Column\":{\"Expression\":{\"SourceRef\":{\"Entity\":\"metrics selection\"}},\"Property\":\"metrics selection\"}}}]},\"columnProperties\":{\"Measure Table.Total Games\":{\"displayName\":\"Total Games\"}},\"drillFilterOtherVisuals\":true,\"hasDefaultSort\":true,\"objects\":{\"valueAxis\":[{\"properties\":{\"showAxisTitle\":{\"expr\":{\"Literal\":{\"Value\":\"false\"}}}}}],\"zoom\":[{\"properties\":{\"show\":{\"expr\":{\"Literal\":{\"Value\":\"true\"}}},\"showOnValueAxis\":{\"expr\":{\"Literal\":{\"Value\":\"false\"}}}}}],\"categoryAxis\":[{\"properties\":{\"showAxisTitle\":{\"expr\":{\"Literal\":{\"Value\":\"false\"}}}}}],\"lineStyles\":[{\"properties\":{\"strokeWidth\":{\"expr\":{\"Literal\":{\"Value\":\"2D\"}}},\"lineChartType\":{\"expr\":{\"Literal\":{\"Value\":\"'smooth'\"}}},\"showMarker\":{\"expr\":{\"Literal\":{\"Value\":\"true\"}}}}}],\"dataPoint\":[{\"properties\":{\"fill\":{\"solid\":{\"color\":{\"expr\":{\"Literal\":{\"Value\":\"'#5F9EA0'\"}}}}}},\"selector\":{\"metadata\":\"Measure Table.Total Games\"}},{\"properties\":{\"fill\":{\"solid\":{\"color\":{\"expr\":{\"Literal\":{\"Value\":\"'#579BD9'\"}}}}}},\"selector\":{\"metadata\":\"Measure Table.AVG Recommendations\"}},{\"properties\":{\"fill\":{\"solid\":{\"color\":{\"expr\":{\"Literal\":{\"Value\":\"'#F08080'\"}}}}}},\"selector\":{\"metadata\":\"Measure Table.Free Games\"}},{\"properties\":{\"fill\":{\"solid\":{\"color\":{\"expr\":{\"ThemeDataColor\":{\"ColorId\":9,\"Percent\":0.6}}}}}},\"selector\":{\"metadata\":\"Measure Table.AVG Price\"}}]},\"vcObjects\":{\"title\":[{\"properties\":{\"show\":{\"expr\":{\"Literal\":{\"Value\":\"false\"}}}}}],\"background\":[{\"properties\":{\"show\":{\"expr\":{\"Literal\":{\"Value\":\"false\"}}}}}]}}}",
          "filters": "[]",
          "height": 291.55,
          "width": 482.08,
          "x": 762.12,
          "y": 195.64,
          "z": 3000.00
        }
      ],
      "width": 1280.00
    },
    {
      "config": "{\"type\":1}",
      "displayName": "Tooltip",
      "displayOption": 3,
      "filters": "[]",
      "height": 240.00,
      "name": "e0e31cbc79b4596b6b6b",
      "ordinal": 1,
      "visualContainers": [
        {
          "config": "{\"name\":\"1efae8538f68be8db60f\",\"layouts\":[{\"id\":0,\"position\":{\"x\":146,\"y\":0,\"z\":7000,\"width\":23,\"height\":240,\"tabOrder\":7000}}],\"singleVisual\":{\"visualType\":\"shape\",\"drillFilterOtherVisuals\":true,\"objects\":{\"shape\":[{\"properties\":{\"tileShape\":{\"expr\":{\"Literal\":{\"Value\":\"'line'\"}}}}}],\"rotation\":[{\"properties\":{\"shapeAngle\":{\"expr\":{\"Literal\":{\"Value\":\"0L\"}}},\"angle\":{\"expr\":{\"Literal\":{\"Value\":\"90D\"}}}}}],\"outline\":[{\"properties\":{\"lineColor\":{\"solid\":{\"color\":{\"expr\":{\"Literal\":{\"Value\":\"'#5F9EA0'\"}}}}}},\"selector\":{\"id\":\"default\"}}],\"shadow\":[{\"properties\":{\"show\":{\"expr\":{\"Literal\":{\"Value\":\"true\"}}}}}]},\"vcObjects\":{\"dropShadow\":[{\"properties\":{\"show\":{\"expr\":{\"Literal\":{\"Value\":\"false\"}}}}}]}},\"howCreated\":\"InsertVisualButton\"}",
          "filters": "[]",
          "height": 240.00,
          "width": 23.00,
          "x": 146.00,
          "y": 0.00,
          "z": 7000.00
        },
        {
          "config": "{\"name\":\"2fa5a70b733bf7bae469\",\"layouts\":[{\"id\":0,\"position\":{\"x\":23,\"y\":0,\"z\":0,\"width\":135,\"height\":87,\"tabOrder\":0}}],\"singleVisual\":{\"visualType\":\"cardVisual\",\"projections\":{\"Data\":[{\"queryRef\":\"Min(fact_steam_games_gl.name)\"}]},\"prototypeQuery\":{\"Version\":2,\"From\":[{\"Name\":\"f\",\"Entity\":\"fact_steam_games_gl\",\"Type\":0}],\"Select\":[{\"Aggregation\":{\"Expression\":{\"Column\":{\"Expression\":{\"SourceRef\":{\"Source\":\"f\"}},\"Property\":\"name\"}},\"Function\":3},\"Name\":\"Min(fact_steam_games_gl.name)\",\"NativeReferenceName\":\"First name\"}]},\"drillFilterOtherVisuals\":true,\"objects\":{\"layout\":[{\"properties\":{\"paddingUniform\":{\"expr\":{\"Literal\":{\"Value\":\"0L\"}}},\"backgroundShow\":{\"expr\":{\"Literal\":{\"Value\":\"false\"}}}},\"selector\":{\"id\":\"default\"}},{\"properties\":{\"autoGrid\":{\"expr\":{\"Literal\":{\"Value\":\"true\"}}}}}],\"fillCustom\":[{\"properties\":{\"show\":{\"expr\":{\"Literal\":{\"Value\":\"false\"}}}}}],\"accentBar\":[{\"properties\":{\"show\":{\"expr\":{\"Literal\":{\"Value\":\"false\"}}},\"color\":{\"solid\":{\"color\":{\"expr\":{\"Literal\":{\"Value\":\"'#5F9EA0'\"}}}}},\"position\":{\"expr\":{\"Literal\":{\"Value\":\"'Top'\"}}},\"width\":{\"expr\":{\"Literal\":{\"Value\":\"13D\"}}}},\"selector\":{\"metadata\":\"Min(fact_steam_games_gl.name)\"}}],\"label\":[{\"properties\":{\"text\":{\"expr\":{\"Literal\":{\"Value\":\"'Top Game'\"}}},\"fontSize\":{\"expr\":{\"Literal\":{\"Value\":\"10D\"}}},\"bold\":{\"expr\":{\"Literal\":{\"Value\":\"true\"}}},\"position\":{\"expr\":{\"Literal\":{\"Value\":\"'aboveValue'\"}}}},\"selector\":{\"metadata\":\"Min(fact_steam_games_gl.name)\"}}],\"spacing\":[{\"properties\":{\"verticalSpacing\":{\"expr\":{\"Literal\":{\"Value\":\"6L\"}}}},\"selector\":{\"metadata\":\"Min(fact_steam_games_gl.name)\"}}],\"value\":[{\"properties\":{\"fontFamily\":{\"expr\":{\"Literal\":{\"Value\":\"'''Segoe UI Bold'', wf_segoe-ui_bold, helvetica, arial, sans-serif'\"}}},\"fontSize\":{\"expr\":{\"Literal\":{\"Value\":\"12D\"}}},\"textWrap\":{\"expr\":{\"Literal\":{\"Value\":\"true\"}}},\"horizontalAlignment\":{\"expr\":{\"Literal\":{\"Value\":\"'left'\"}}},\"fontColor\":{\"solid\":{\"color\":{\"expr\":{\"Literal\":{\"Value\":\"'#5F9EA0'\"}}}}},\"bold\":{\"expr\":{\"Literal\":{\"Value\":\"false\"}}}},\"selector\":{\"metadata\":\"Min(fact_steam_games_gl.name)\"}},{\"properties\":{\"fontSize\":{\"expr\":{\"Literal\":{\"Value\":\"15D\"}}}},\"selector\":{\"id\":\"default\"}}],\"padding\":[{\"properties\":{\"paddingUniform\":{\"expr\":{\"Literal\":{\"Value\":\"7L\"}}}},\"selector\":{\"id\":\"default\"}}],\"divider\":[{\"properties\":{\"show\":{\"expr\":{\"Literal\":{\"Value\":\"false\"}}}},\"selector\":{\"metadata\":\"Min(fact_steam_games_gl.name)\"}}],\"outline\":[{\"properties\":{\"show\":{\"expr\":{\"Literal\":{\"Value\":\"false\"}}}},\"selector\":{\"metadata\":\"Min(fact_steam_games_gl.name)\"}}]},\"vcObjects\":{\"background\":[{\"properties\":{\"show\":{\"expr\":{\"Literal\":{\"Value\":\"false\"}}}}}],\"padding\":[{\"properties\":{\"top\":{\"expr\":{\"Literal\":{\"Value\":\"0D\"}}},\"left\":{\"expr\":{\"Literal\":{\"Value\":\"0D\"}}},\"bottom\":{\"expr\":{\"Literal\":{\"Value\":\"0D\"}}},\"right\":{\"expr\":{\"Literal\":{\"Value\":\"0D\"}}}}}],\"dropShadow\":[{\"properties\":{\"show\":{\"expr\":{\"Literal\":{\"Value\":\"false\"}}}}}],\"visualHeader\":[{\"properties\":{\"show\":{\"expr\":{\"Literal\":{\"Value\":\"true\"}}}}}]}}}",
          "filters": "[{\"name\":\"7254024efd790255421c\",\"expression\":{\"Column\":{\"Expression\":{\"SourceRef\":{\"Entity\":\"fact_steam_games_gl\"}},\"Property\":\"name\"}},\"filter\":{\"Version\":2,\"From\":[{\"Name\":\"subquery\",\"Expression\":{\"Subquery\":{\"Query\":{\"Version\":2,\"From\":[{\"Name\":\"f\",\"Entity\":\"fact_steam_games_gl\",\"Type\":0},{\"Name\":\"m\",\"Entity\":\"Measure Table\",\"Type\":0}],\"Select\":[{\"Column\":{\"Expression\":{\"SourceRef\":{\"Source\":\"f\"}},\"Property\":\"name\"},\"Name\":\"field\"}],\"OrderBy\":[{\"Direction\":2,\"Expression\":{\"Measure\":{\"Expression\":{\"SourceRef\":{\"Source\":\"m\"}},\"Property\":\"AVG Recommendations\"}}}],\"Top\":1}}},\"Type\":2},{\"Name\":\"f\",\"Entity\":\"fact_steam_games_gl\",\"Type\":0}],\"Where\":[{\"Condition\":{\"In\":{\"Expressions\":[{\"Column\":{\"Expression\":{\"SourceRef\":{\"Source\":\"f\"}},\"Property\":\"name\"}}],\"Table\":{\"SourceRef\":{\"Source\":\"subquery\"}}}}}]},\"type\":\"TopN\",\"howCreated\":1}]",
          "height": 87.00,
          "width": 135.00,
          "x": 23.00,
          "y": 0.00,
          "z": 0.00
        },
        {
          "config": "{\"name\":\"302c6314597b8bc692ff\",\"layouts\":[{\"id\":0,\"position\":{\"x\":3,\"y\":0,\"z\":4000,\"width\":23,\"height\":240,\"tabOrder\":4000}}],\"singleVisual\":{\"visualType\":\"shape\",\"drillFilterOtherVisuals\":true,\"objects\":{\"shape\":[{\"properties\":{\"tileShape\":{\"expr\":{\"Literal\":{\"Value\":\"'line'\"}}}}}],\"rotation\":[{\"properties\":{\"shapeAngle\":{\"expr\":{\"Literal\":{\"Value\":\"0L\"}}},\"angle\":{\"expr\":{\"Literal\":{\"Value\":\"90D\"}}}}}],\"outline\":[{\"properties\":{\"lineColor\":{\"solid\":{\"color\":{\"expr\":{\"Literal\":{\"Value\":\"'#5F9EA0'\"}}}}}},\"selector\":{\"id\":\"default\"}}],\"shadow\":[{\"properties\":{\"show\":{\"expr\":{\"Literal\":{\"Value\":\"true\"}}}}}]},\"vcObjects\":{\"dropShadow\":[{\"properties\":{\"show\":{\"expr\":{\"Literal\":{\"Value\":\"false\"}}}}}]}},\"howCreated\":\"InsertVisualButton\"}",
          "filters": "[]",
          "height": 240.00,
          "width": 23.00,
          "x": 3.00,
          "y": 0.00,
          "z": 4000.00
        },
        {
          "config": "{\"name\":\"6b297789571b74ff26a3\",\"layouts\":[{\"id\":0,\"position\":{\"x\":169,\"y\":118,\"z\":5000,\"width\":144,\"height\":113,\"tabOrder\":5000}}],\"singleVisual\":{\"visualType\":\"advancedSlicerVisual\",\"projections\":{\"Values\":[{\"queryRef\":\"dim_genres_gl.genre\"}]},\"prototypeQuery\":{\"Version\":2,\"From\":[{\"Name\":\"d\",\"Entity\":\"dim_genres_gl\",\"Type\":0}],\"Select\":[{\"Column\":{\"Expression\":{\"SourceRef\":{\"Source\":\"d\"}},\"Property\":\"genre\"},\"Name\":\"dim_genres_gl.genre\",\"NativeReferenceName\":\"genre\"}]},\"drillFilterOtherVisuals\":true,\"objects\":{\"data\":[{\"properties\":{}}],\"general\":[{\"properties\":{}}],\"layout\":[{\"properties\":{\"columnCount\":{\"expr\":{\"Literal\":{\"Value\":\"1L\"}}},\"rowCount\":{\"expr\":{\"Literal\":{\"Value\":\"2L\"}}},\"cellPadding\":{\"expr\":{\"Literal\":{\"Value\":\"0L\"}}},\"style\":{\"expr\":{\"Literal\":{\"Value\":\"'Table'\"}}},\"orientation\":{\"expr\":{\"Literal\":{\"Value\":\"1D\"}}},\"maxTiles\":{\"expr\":{\"Literal\":{\"Value\":\"3L\"}}},\"autoGrid\":{\"expr\":{\"Literal\":{\"Value\":\"true\"}}}}}],\"value\":[{\"properties\":{\"fontSize\":{\"expr\":{\"Literal\":{\"Value\":\"8D\"}}},\"horizontalAlignment\":{\"expr\":{\"Literal\":{\"Value\":\"'center'\"}}},\"fontColor\":{\"solid\":{\"color\":{\"expr\":{\"Literal\":{\"Value\":\"'#5F9EA0'\"}}}}},\"fontFamily\":{\"expr\":{\"Literal\":{\"Value\":\"'''Segoe UI Bold'', wf_segoe-ui_bold, helvetica, arial, sans-serif'\"}}}},\"selector\":{\"id\":\"default\"}}],\"overFlow\":[{\"properties\":{\"overFlowDirection\":{\"expr\":{\"Literal\":{\"Value\":\"0D\"}}}}}],\"padding\":[{\"properties\":{\"paddingSelection\":{\"expr\":{\"Literal\":{\"Value\":\"'Custom'\"}}},\"topMargin\":{\"expr\":{\"Literal\":{\"Value\":\"0L\"}}},\"leftMargin\":{\"expr\":{\"Literal\":{\"Value\":\"0L\"}}},\"bottomMargin\":{\"expr\":{\"Literal\":{\"Value\":\"0L\"}}},\"rightMargin\":{\"expr\":{\"Literal\":{\"Value\":\"0L\"}}}},\"selector\":{\"id\":\"default\"}}],\"fillCustom\":[{\"properties\":{\"show\":{\"expr\":{\"Literal\":{\"Value\":\"false\"}}}},\"selector\":{\"id\":\"default\"}}]},\"vcObjects\":{\"padding\":[{\"properties\":{\"bottom\":{\"expr\":{\"Literal\":{\"Value\":\"0D\"}}},\"left\":{\"expr\":{\"Literal\":{\"Value\":\"0D\"}}},\"right\":{\"expr\":{\"Literal\":{\"Value\":\"0D\"}}}}}],\"background\":[{\"properties\":{\"show\":{\"expr\":{\"Literal\":{\"Value\":\"false\"}}}}}],\"border\":[{\"properties\":{\"show\":{\"expr\":{\"Literal\":{\"Value\":\"false\"}}}}}],\"title\":[{\"properties\":{\"show\":{\"expr\":{\"Literal\":{\"Value\":\"true\"}}},\"fontFamily\":{\"expr\":{\"Literal\":{\"Value\":\"'''Segoe UI'', wf_segoe-ui_normal, helvetica, arial, sans-serif'\"}}},\"bold\":{\"expr\":{\"Literal\":{\"Value\":\"true\"}}},\"fontSize\":{\"expr\":{\"Literal\":{\"Value\":\"10D\"}}},\"fontColor\":{\"solid\":{\"color\":{\"expr\":{\"ThemeDataColor\":{\"ColorId\":1,\"Percent\":0.4}}}}},\"text\":{\"expr\":{\"Literal\":{\"Value\":\"'Genre'\"}}}}}]}}}",
          "filters": "[]",
          "height": 113.00,
          "width": 144.00,
          "x": 169.00,
          "y": 118.00,
          "z": 5000.00
        },
        {
          "config": "{\"name\":\"728bc01ea222b5b14e13\",\"layouts\":[{\"id\":0,\"position\":{\"x\":24,\"y\":101,\"z\":2000,\"width\":173,\"height\":83,\"tabOrder\":2000}}],\"singleVisual\":{\"visualType\":\"cardVisual\",\"projections\":{\"Data\":[{\"queryRef\":\"Measure Table.Total Recommendations\"}]},\"prototypeQuery\":{\"Version\":2,\"From\":[{\"Name\":\"m\",\"Entity\":\"Measure Table\",\"Type\":0}],\"Select\":[{\"Measure\":{\"Expression\":{\"SourceRef\":{\"Source\":\"m\"}},\"Property\":\"Total Recommendations\"},\"Name\":\"Measure Table.Total Recommendations\",\"NativeReferenceName\":\"Total Recommendations\"}],\"OrderBy\":[{\"Direction\":2,\"Expression\":{\"Measure\":{\"Expression\":{\"SourceRef\":{\"Source\":\"m\"}},\"Property\":\"Total Recommendations\"}}}]},\"columnProperties\":{\"Measure Table.Total Recommendations\":{\"formatString\":\"#,0\"}},\"drillFilterOtherVisuals\":true,\"hasDefaultSort\":true,\"objects\":{\"layout\":[{\"properties\":{\"paddingUniform\":{\"expr\":{\"Literal\":{\"Value\":\"0L\"}}},\"backgroundShow\":{\"expr\":{\"Literal\":{\"Value\":\"false\"}}}},\"selector\":{\"id\":\"default\"}},{\"properties\":{\"autoGrid\":{\"expr\":{\"Literal\":{\"Value\":\"true\"}}}}}],\"fillCustom\":[{\"properties\":{\"show\":{\"expr\":{\"Literal\":{\"Value\":\"false\"}}}}}],\"value\":[{\"properties\":{\"fontSize\":{\"expr\":{\"Literal\":{\"Value\":\"15D\"}}}},\"selector\":{\"id\":\"default\"}},{\"properties\":{\"fontFamily\":{\"expr\":{\"Literal\":{\"Value\":\"'''Segoe UI Bold'', wf_segoe-ui_bold, helvetica, arial, sans-serif'\"}}},\"fontColor\":{\"solid\":{\"color\":{\"expr\":{\"Literal\":{\"Value\":\"'#5F9EA0'\"}}}}},\"labelDisplayUnits\":{\"expr\":{\"Literal\":{\"Value\":\"1D\"}}}},\"selector\":{\"metadata\":\"Measure Table.Total Recommendations\"}}],\"padding\":[{\"properties\":{\"paddingUniform\":{\"expr\":{\"Literal\":{\"Value\":\"7L\"}}}},\"selector\":{\"id\":\"default\"}}],\"label\":[{\"properties\":{\"text\":{\"expr\":{\"Literal\":{\"Value\":\"'Recommendations'\"}}},\"fontSize\":{\"expr\":{\"Literal\":{\"Value\":\"10D\"}}},\"bold\":{\"expr\":{\"Literal\":{\"Value\":\"true\"}}},\"position\":{\"expr\":{\"Literal\":{\"Value\":\"'aboveValue'\"}}}},\"selector\":{\"metadata\":\"Measure Table.Total Recommendations\"}}],\"outline\":[{\"properties\":{\"show\":{\"expr\":{\"Literal\":{\"Value\":\"false\"}}}},\"selector\":{\"id\":\"default\"}}],\"divider\":[{\"properties\":{\"show\":{\"expr\":{\"Literal\":{\"Value\":\"false\"}}}},\"selector\":{\"id\":\"default\"}}]},\"vcObjects\":{\"background\":[{\"properties\":{\"show\":{\"expr\":{\"Literal\":{\"Value\":\"false\"}}}}}],\"padding\":[{\"properties\":{\"top\":{\"expr\":{\"Literal\":{\"Value\":\"0D\"}}},\"left\":{\"expr\":{\"Literal\":{\"Value\":\"0D\"}}},\"bottom\":{\"expr\":{\"Literal\":{\"Value\":\"0D\"}}},\"right\":{\"expr\":{\"Literal\":{\"Value\":\"0D\"}}}}}],\"dropShadow\":[{\"properties\":{\"show\":{\"expr\":{\"Literal\":{\"Value\":\"false\"}}}}}],\"visualHeader\":[{\"properties\":{\"show\":{\"expr\":{\"Literal\":{\"Value\":\"true\"}}}}}]}}}",
          "filters": "[{\"name\":\"7254024efd790255421c\",\"expression\":{\"Column\":{\"Expression\":{\"SourceRef\":{\"Entity\":\"fact_steam_games_gl\"}},\"Property\":\"name\"}},\"filter\":{\"Version\":2,\"From\":[{\"Name\":\"subquery\",\"Expression\":{\"Subquery\":{\"Query\":{\"Version\":2,\"From\":[{\"Name\":\"f\",\"Entity\":\"fact_steam_games_gl\",\"Type\":0},{\"Name\":\"m\",\"Entity\":\"Measure Table\",\"Type\":0}],\"Select\":[{\"Column\":{\"Expression\":{\"SourceRef\":{\"Source\":\"f\"}},\"Property\":\"name\"},\"Name\":\"field\"}],\"OrderBy\":[{\"Direction\":2,\"Expression\":{\"Measure\":{\"Expression\":{\"SourceRef\":{\"Source\":\"m\"}},\"Property\":\"AVG Recommendations\"}}}],\"Top\":1}}},\"Type\":2},{\"Name\":\"f\",\"Entity\":\"fact_steam_games_gl\",\"Type\":0}],\"Where\":[{\"Condition\":{\"In\":{\"Expressions\":[{\"Column\":{\"Expression\":{\"SourceRef\":{\"Source\":\"f\"}},\"Property\":\"name\"}}],\"Table\":{\"SourceRef\":{\"Source\":\"subquery\"}}}}}]},\"type\":\"TopN\",\"howCreated\":1}]",
          "height": 83.00,
          "width": 173.00,
          "x": 24.00,
          "y": 101.00,
          "z": 2000.00
        },
        {
          "config": "{\"name\":\"7bc14e20783bb80fcc1b\",\"layouts\":[{\"id\":0,\"position\":{\"x\":24,\"y\":53,\"z\":1000,\"width\":147,\"height\":83,\"tabOrder\":1000}}],\"singleVisual\":{\"visualType\":\"cardVisual\",\"projections\":{\"Data\":[{\"queryRef\":\"Measure Table.Total Games\"}]},\"prototypeQuery\":{\"Version\":2,\"From\":[{\"Name\":\"m\",\"Entity\":\"Measure Table\",\"Type\":0}],\"Select\":[{\"Measure\":{\"Expression\":{\"SourceRef\":{\"Source\":\"m\"}},\"Property\":\"Total Games\"},\"Name\":\"Measure Table.Total Games\",\"NativeReferenceName\":\"Total Games\"}],\"OrderBy\":[{\"Direction\":2,\"Expression\":{\"Measure\":{\"Expression\":{\"SourceRef\":{\"Source\":\"m\"}},\"Property\":\"Total Games\"}}}]},\"drillFilterOtherVisuals\":true,\"hasDefaultSort\":true,\"objects\":{\"layout\":[{\"properties\":{\"paddingUniform\":{\"expr\":{\"Literal\":{\"Value\":\"0L\"}}},\"backgroundShow\":{\"expr\":{\"Literal\":{\"Value\":\"false\"}}}},\"selector\":{\"id\":\"default\"}},{\"properties\":{\"autoGrid\":{\"expr\":{\"Literal\":{\"Value\":\"true\"}}}}}],\"fillCustom\":[{\"properties\":{\"show\":{\"expr\":{\"Literal\":{\"Value\":\"false\"}}}}}],\"value\":[{\"properties\":{\"fontSize\":{\"expr\":{\"Literal\":{\"Value\":\"15D\"}}}},\"selector\":{\"id\":\"default\"}},{\"properties\":{\"fontColor\":{\"solid\":{\"color\":{\"expr\":{\"Literal\":{\"Value\":\"'#5F9EA0'\"}}}}},\"fontFamily\":{\"expr\":{\"Literal\":{\"Value\":\"'''Segoe UI Bold'', wf_segoe-ui_bold, helvetica, arial, sans-serif'\"}}}},\"selector\":{\"metadata\":\"Measure Table.Total Games\"}}],\"padding\":[{\"properties\":{\"paddingUniform\":{\"expr\":{\"Literal\":{\"Value\":\"7L\"}}}},\"selector\":{\"id\":\"default\"}}],\"label\":[{\"properties\":{\"fontSize\":{\"expr\":{\"Literal\":{\"Value\":\"10D\"}}},\"bold\":{\"expr\":{\"Literal\":{\"Value\":\"true\"}}},\"position\":{\"expr\":{\"Literal\":{\"Value\":\"'aboveValue'\"}}}},\"selector\":{\"metadata\":\"Measure Table.Total Games\"}}],\"outline\":[{\"properties\":{\"show\":{\"expr\":{\"Literal\":{\"Value\":\"false\"}}}},\"selector\":{\"metadata\":\"Measure Table.Total Games\"}}],\"divider\":[{\"properties\":{\"show\":{\"expr\":{\"Literal\":{\"Value\":\"false\"}}}},\"selector\":{\"metadata\":\"Measure Table.Total Games\"}}]},\"vcObjects\":{\"background\":[{\"properties\":{\"show\":{\"expr\":{\"Literal\":{\"Value\":\"false\"}}}}}],\"padding\":[{\"properties\":{\"top\":{\"expr\":{\"Literal\":{\"Value\":\"0D\"}}},\"left\":{\"expr\":{\"Literal\":{\"Value\":\"0D\"}}},\"bottom\":{\"expr\":{\"Literal\":{\"Value\":\"0D\"}}},\"right\":{\"expr\":{\"Literal\":{\"Value\":\"0D\"}}}}}],\"dropShadow\":[{\"properties\":{\"show\":{\"expr\":{\"Literal\":{\"Value\":\"false\"}}}}}],\"visualHeader\":[{\"properties\":{\"show\":{\"expr\":{\"Literal\":{\"Value\":\"true\"}}}}}]}}}",
          "filters": "[{\"name\":\"7254024efd790255421c\",\"expression\":{\"Column\":{\"Expression\":{\"SourceRef\":{\"Entity\":\"fact_steam_games_gl\"}},\"Property\":\"name\"}},\"filter\":{\"Version\":2,\"From\":[{\"Name\":\"subquery\",\"Expression\":{\"Subquery\":{\"Query\":{\"Version\":2,\"From\":[{\"Name\":\"f\",\"Entity\":\"fact_steam_games_gl\",\"Type\":0},{\"Name\":\"m\",\"Entity\":\"Measure Table\",\"Type\":0}],\"Select\":[{\"Column\":{\"Expression\":{\"SourceRef\":{\"Source\":\"f\"}},\"Property\":\"name\"},\"Name\":\"field\"}],\"OrderBy\":[{\"Direction\":2,\"Expression\":{\"Measure\":{\"Expression\":{\"SourceRef\":{\"Source\":\"m\"}},\"Property\":\"AVG Recommendations\"}}}],\"Top\":1}}},\"Type\":2},{\"Name\":\"f\",\"Entity\":\"fact_steam_games_gl\",\"Type\":0}],\"Where\":[{\"Condition\":{\"In\":{\"Expressions\":[{\"Column\":{\"Expression\":{\"SourceRef\":{\"Source\":\"f\"}},\"Property\":\"name\"}}],\"Table\":{\"SourceRef\":{\"Source\":\"subquery\"}}}}}]},\"type\":\"TopN\",\"howCreated\":1}]",
          "height": 83.00,
          "width": 147.00,
          "x": 24.00,
          "y": 53.00,
          "z": 1000.00
        },
        {
          "config": "{\"name\":\"8e12cbbf4a1785bd7e62\",\"layouts\":[{\"id\":0,\"position\":{\"x\":24,\"y\":149,\"z\":3000,\"width\":173,\"height\":91,\"tabOrder\":3000}}],\"singleVisual\":{\"visualType\":\"cardVisual\",\"projections\":{\"Data\":[{\"queryRef\":\"Measure Table.AVG Price\"}]},\"prototypeQuery\":{\"Version\":2,\"From\":[{\"Name\":\"m\",\"Entity\":\"Measure Table\",\"Type\":0}],\"Select\":[{\"Measure\":{\"Expression\":{\"SourceRef\":{\"Source\":\"m\"}},\"Property\":\"AVG Price\"},\"Name\":\"Measure Table.AVG Price\",\"NativeReferenceName\":\"AVG Price\"}],\"OrderBy\":[{\"Direction\":2,\"Expression\":{\"Measure\":{\"Expression\":{\"SourceRef\":{\"Source\":\"m\"}},\"Property\":\"AVG Price\"}}}]},\"columnProperties\":{\"Measure Table.Total Recommendations\":{\"formatString\":null},\"Measure Table.AVG Price\":{\"formatString\":\"\\\\$#,0.###############;(\\\\$#,0.###############);\\\\$#,0.###############\"}},\"drillFilterOtherVisuals\":true,\"hasDefaultSort\":true,\"objects\":{\"layout\":[{\"properties\":{\"paddingUniform\":{\"expr\":{\"Literal\":{\"Value\":\"0L\"}}},\"backgroundShow\":{\"expr\":{\"Literal\":{\"Value\":\"false\"}}}},\"selector\":{\"id\":\"default\"}},{\"properties\":{\"autoGrid\":{\"expr\":{\"Literal\":{\"Value\":\"true\"}}}}}],\"fillCustom\":[{\"properties\":{\"show\":{\"expr\":{\"Literal\":{\"Value\":\"false\"}}}}}],\"value\":[{\"properties\":{\"fontSize\":{\"expr\":{\"Literal\":{\"Value\":\"15D\"}}}},\"selector\":{\"id\":\"default\"}},{\"properties\":{\"bold\":{\"expr\":{\"Literal\":{\"Value\":\"false\"}}},\"fontFamily\":{\"expr\":{\"Literal\":{\"Value\":\"'''Segoe UI Bold'', wf_segoe-ui_bold, helvetica, arial, sans-serif'\"}}},\"fontColor\":{\"solid\":{\"color\":{\"expr\":{\"Literal\":{\"Value\":\"'#5F9EA0'\"}}}}}},\"selector\":{\"metadata\":\"Measure Table.AVG Price\"}}],\"padding\":[{\"properties\":{\"paddingUniform\":{\"expr\":{\"Literal\":{\"Value\":\"7L\"}}}},\"selector\":{\"id\":\"default\"}}],\"outline\":[{\"properties\":{\"show\":{\"expr\":{\"Literal\":{\"Value\":\"false\"}}}},\"selector\":{\"id\":\"default\"}}],\"divider\":[{\"properties\":{\"show\":{\"expr\":{\"Literal\":{\"Value\":\"false\"}}}},\"selector\":{\"id\":\"default\"}}],\"label\":[{\"properties\":{\"text\":{\"expr\":{\"Literal\":{\"Value\":\"'Average Price'\"}}},\"bold\":{\"expr\":{\"Literal\":{\"Value\":\"true\"}}},\"fontSize\":{\"expr\":{\"Literal\":{\"Value\":\"10D\"}}},\"position\":{\"expr\":{\"Literal\":{\"Value\":\"'aboveValue'\"}}}},\"selector\":{\"metadata\":\"Measure Table.AVG Price\"}}]},\"vcObjects\":{\"background\":[{\"properties\":{\"show\":{\"expr\":{\"Literal\":{\"Value\":\"false\"}}}}}],\"padding\":[{\"properties\":{\"top\":{\"expr\":{\"Literal\":{\"Value\":\"0D\"}}},\"left\":{\"expr\":{\"Literal\":{\"Value\":\"0D\"}}},\"bottom\":{\"expr\":{\"Literal\":{\"Value\":\"0D\"}}},\"right\":{\"expr\":{\"Literal\":{\"Value\":\"0D\"}}}}}],\"dropShadow\":[{\"properties\":{\"show\":{\"expr\":{\"Literal\":{\"Value\":\"false\"}}}}}],\"visualHeader\":[{\"properties\":{\"show\":{\"expr\":{\"Literal\":{\"Value\":\"true\"}}}}}]}}}",
          "filters": "[{\"name\":\"7254024efd790255421c\",\"expression\":{\"Column\":{\"Expression\":{\"SourceRef\":{\"Entity\":\"fact_steam_games_gl\"}},\"Property\":\"name\"}},\"filter\":{\"Version\":2,\"From\":[{\"Name\":\"subquery\",\"Expression\":{\"Subquery\":{\"Query\":{\"Version\":2,\"From\":[{\"Name\":\"f\",\"Entity\":\"fact_steam_games_gl\",\"Type\":0},{\"Name\":\"m\",\"Entity\":\"Measure Table\",\"Type\":0}],\"Select\":[{\"Column\":{\"Expression\":{\"SourceRef\":{\"Source\":\"f\"}},\"Property\":\"name\"},\"Name\":\"field\"}],\"OrderBy\":[{\"Direction\":2,\"Expression\":{\"Measure\":{\"Expression\":{\"SourceRef\":{\"Source\":\"m\"}},\"Property\":\"AVG Recommendations\"}}}],\"Top\":1}}},\"Type\":2},{\"Name\":\"f\",\"Entity\":\"fact_steam_games_gl\",\"Type\":0}],\"Where\":[{\"Condition\":{\"In\":{\"Expressions\":[{\"Column\":{\"Expression\":{\"SourceRef\":{\"Source\":\"f\"}},\"Property\":\"name\"}}],\"Table\":{\"SourceRef\":{\"Source\":\"subquery\"}}}}}]},\"type\":\"TopN\",\"howCreated\":1}]",
          "height": 91.00,
          "width": 173.00,
          "x": 24.00,
          "y": 149.00,
          "z": 3000.00
        },
        {
          "config": "{\"name\":\"fb9317cd5055d55b3c84\",\"layouts\":[{\"id\":0,\"position\":{\"x\":169,\"y\":14,\"z\":6000,\"width\":144,\"height\":104,\"tabOrder\":6000}}],\"singleVisual\":{\"visualType\":\"advancedSlicerVisual\",\"projections\":{\"Values\":[{\"queryRef\":\"dim_categories_gl.category\"}]},\"prototypeQuery\":{\"Version\":2,\"From\":[{\"Name\":\"d\",\"Entity\":\"dim_categories_gl\",\"Type\":0}],\"Select\":[{\"Column\":{\"Expression\":{\"SourceRef\":{\"Source\":\"d\"}},\"Property\":\"category\"},\"Name\":\"dim_categories_gl.category\",\"NativeReferenceName\":\"category\"}]},\"drillFilterOtherVisuals\":true,\"objects\":{\"data\":[{\"properties\":{}}],\"general\":[{\"properties\":{}}],\"layout\":[{\"properties\":{\"columnCount\":{\"expr\":{\"Literal\":{\"Value\":\"1L\"}}},\"rowCount\":{\"expr\":{\"Literal\":{\"Value\":\"2L\"}}},\"cellPadding\":{\"expr\":{\"Literal\":{\"Value\":\"0L\"}}},\"style\":{\"expr\":{\"Literal\":{\"Value\":\"'Table'\"}}},\"orientation\":{\"expr\":{\"Literal\":{\"Value\":\"1D\"}}},\"maxTiles\":{\"expr\":{\"Literal\":{\"Value\":\"3L\"}}},\"autoGrid\":{\"expr\":{\"Literal\":{\"Value\":\"true\"}}}}}],\"value\":[{\"properties\":{\"fontSize\":{\"expr\":{\"Literal\":{\"Value\":\"8D\"}}},\"horizontalAlignment\":{\"expr\":{\"Literal\":{\"Value\":\"'center'\"}}},\"fontColor\":{\"solid\":{\"color\":{\"expr\":{\"Literal\":{\"Value\":\"'#5F9EA0'\"}}}}},\"fontFamily\":{\"expr\":{\"Literal\":{\"Value\":\"'''Segoe UI Bold'', wf_segoe-ui_bold, helvetica, arial, sans-serif'\"}}}},\"selector\":{\"id\":\"default\"}}],\"overFlow\":[{\"properties\":{\"overFlowDirection\":{\"expr\":{\"Literal\":{\"Value\":\"0D\"}}}}}],\"padding\":[{\"properties\":{\"paddingSelection\":{\"expr\":{\"Literal\":{\"Value\":\"'Custom'\"}}},\"topMargin\":{\"expr\":{\"Literal\":{\"Value\":\"0L\"}}},\"leftMargin\":{\"expr\":{\"Literal\":{\"Value\":\"0L\"}}},\"bottomMargin\":{\"expr\":{\"Literal\":{\"Value\":\"0L\"}}},\"rightMargin\":{\"expr\":{\"Literal\":{\"Value\":\"0L\"}}}},\"selector\":{\"id\":\"default\"}}],\"fillCustom\":[{\"properties\":{\"show\":{\"expr\":{\"Literal\":{\"Value\":\"false\"}}}},\"selector\":{\"id\":\"default\"}}]},\"vcObjects\":{\"padding\":[{\"properties\":{\"bottom\":{\"expr\":{\"Literal\":{\"Value\":\"0D\"}}},\"left\":{\"expr\":{\"Literal\":{\"Value\":\"0D\"}}},\"right\":{\"expr\":{\"Literal\":{\"Value\":\"0D\"}}}}}],\"background\":[{\"properties\":{\"show\":{\"expr\":{\"Literal\":{\"Value\":\"false\"}}}}}],\"border\":[{\"properties\":{\"show\":{\"expr\":{\"Literal\":{\"Value\":\"false\"}}}}}],\"title\":[{\"properties\":{\"show\":{\"expr\":{\"Literal\":{\"Value\":\"true\"}}},\"fontFamily\":{\"expr\":{\"Literal\":{\"Value\":\"'''Segoe UI'', wf_segoe-ui_normal, helvetica, arial, sans-serif'\"}}},\"bold\":{\"expr\":{\"Literal\":{\"Value\":\"true\"}}},\"fontSize\":{\"expr\":{\"Literal\":{\"Value\":\"10D\"}}},\"fontColor\":{\"solid\":{\"color\":{\"expr\":{\"ThemeDataColor\":{\"ColorId\":1,\"Percent\":0.4}}}}},\"text\":{\"expr\":{\"Literal\":{\"Value\":\"'Category'\"}}}}}]}}}",
          "filters": "[]",
          "height": 104.00,
          "width": 144.00,
          "x": 169.00,
          "y": 14.00,
          "z": 6000.00
        }
      ],
      "width": 320.00
    }
  ]
}